Workbook

Sheet Guía
A1: T2 – Teoría de Juegos: 3 jugadores y competencias de empresas
A2: Libro de cálculo que respalda el informe en Word.
A5: Mapa de la lista de cotejo → hoja del libro
A6: Criterio | B6: Puntos | C6: Hoja(s) | D6: Qué mostrar en el Word
A7: Empresa | B7: 3 | C7: Empresas | D7: Descripción de los tres negocios y de por qué compiten (mismo rubro, mismo cliente).
A8: Matriz 3J – Datos cuantitativos | B8: 4 | C8: Ventas_*, Datos_3J | D8: Ventas diarias, precios, costos; ingreso mensual por empresa y producto.
A9: Matriz 3J – Proceso de cada terna | B9: 4 | C9: Terna_Proceso | D9: Participaciones, reparto del ingreso de quien sale, fórmula de las 8 ternas.
A10: Matriz 3J – Suma nula e interpretación | B10: 6 | C10: Matriz_3J | D10: Matriz original y suma nula, mejores respuestas, Nash y lectura de 3 ternas.
A11: Competencia – Datos cuantitativos | B11: 4 | C11: Datos_Comp | D11: 30 observaciones emparejadas (q1,q2,p1,p2) y costos.
A12: Competencia – Generación de funciones | B12: 4 | C12: Regresión | D12: Ecuaciones normales, Gauss-Jordan, comparación con LINEST, R².
A13: Competencia – Solución no cooperativa | B13: 3 | C13: Nash | D13: FOC, curvas de reacción, equilibrio, 2º orden, gráfico.
A14: Competencia – Solución cooperativa | B14: 3 | C14: Cooperativa | D14: Maximización de u1+u2, comparación con Nash, tentación de desviarse.
A15: Competencia – Análisis comparativo | B15: 2 | C15: Comparativo | D15: Observado vs. Nash vs. cooperativo (S/ por día y por mes).
A16: Conclusiones | B16: 2 | C16: Resumen_Word | D16: Cifras clave para redactar conclusiones.
A18: Cómo leer el libro
A19: Azul | B19: Dato de entrada (editable): ventas, precios, costos, series de precio, parámetros.
A20: Negro | B20: Fórmula calculada en la misma hoja.
A21: Verde | B21: Vínculo a otra hoja.
A22: Amarillo | B22: Campo por completar con información propia del negocio.
A24: Supuestos y límites del modelo
A25: Juego de 3 jugadores: cada empresa decide si OFRECE o NO el producto en disputa; pago = ingreso mensual menos la base media (suma nula), como en la guía de la semana 7/8.
A26: Competencia en CANTIDADES (Cournot): la teoría de las semanas 8 y 9 es idéntica para precios y cantidades; se eligió cantidades porque el dato observable de cada bodega es lo vendido por día.
A27: Funciones de demanda inversa p_i = α_i + β_i·q_i + γ_i·q_j estimadas con 30 observaciones emparejadas por número de día (los negocios no se midieron en las mismas fechas).
A28: Precios de venta, costos unitarios y la serie diaria de precios son supuestos de referencia editables (hojas Datos_3J y Datos_Comp); si se reemplazan por datos propios, todo el libro se recalcula.
A29: Utilidad = (precio − costo)·cantidad; no se incluyen costos fijos.

Sheet Empresas
A1: Empresas analizadas
A2: Tres negocios del mismo rubro (comercio minorista de abarrotes) que compiten por el mismo cliente de barrio.
A4: Campo | B4: Bodega La Esquina de Ana | C4: Berry Blue | D4: Bodega Martina
A5: Empresa | B5: Bodega "La Esquina de Ana" | C5: Fuente de Soda Berry Blue | D5: Bodega Martina
A6: Ubicación | B6: [completar] | C6: Los Olivos, Lima, Perú | D6: [completar]
A7: Formalidad / registro | B7: [completar] | C7: Negocio familiar; las cifras provienen del registro propio de ventas | D7: [completar]
A8: Fundación e historia | B8: [completar] | C8: Fundado en 2022. Fuente de soda que ofrece diversidad de productos alimentarios. | D8: [completar]
A9: Rubro | B9: Comercio minorista – abarrotes | C9: Comercio minorista – abarrotes | D9: Comercio minorista – abarrotes
A10: Productos analizados | B10: Aceite, Atún, Gaseosa, Cerveza, Snacks, Azúcar y Leche | C10: Aceite, Atún, Gaseosa, Cerveza, Snacks, Azúcar y Leche | D10: Aceite, Atún, Gaseosa, Cerveza, Snacks, Azúcar y Leche
A11: Proveedores | B11: [completar] | C11: Proveedores y mercados mayoristas | D11: [completar]
A12: Clientes | B12: [completar] | C12: En su mayoría personas al paso | D12: [completar]
A13: Unidad de medida | B13: Unidades vendidas por día | C13: Unidades vendidas por día | D13: Unidades vendidas por día
A14: Periodo de datos | B14: 30 días – del 28 de junio al 27 de julio de 2025 | C14: 31 días – del 01 al 31 de agosto de 2026 | D14: 30 días – del 01 al 30 de setiembre de 2026
A16: Indicadores calculados desde las ventas
A17: Venta media diaria (todas las unidades) | B17: =Datos_3J!B47 -> 27.933333 | C17: =Datos_3J!C47 -> 30 | D17: =Datos_3J!D47 -> 28.733333
A18: Producto más vendido (unid/día) | B18: =INDEX(Datos_3J!$A$40:$A$46,MATCH(MAX(Datos_3J!B40:B46),Datos_3J!B40:B46,0)) -> Cerveza | C18: =INDEX(Datos_3J!$A$40:$A$46,MATCH(MAX(Datos_3J!C40:C46),Datos_3J!C40:C46,0)) -> Atún | D18: =INDEX(Datos_3J!$A$40:$A$46,MATCH(MAX(Datos_3J!D40:D46),Datos_3J!D40:D46,0)) -> Cerveza
A19: Producto en disputa (k) | B19: =Datos_3J!$B$5 -> Cerveza | C19: =Datos_3J!$B$5 -> Cerveza | D19: =Datos_3J!$B$5 -> Cerveza
A20: Ventas diarias medias de k (unid) | B20: =INDEX(Datos_3J!B40:B46,Datos_3J!$B$6) -> 13.766667 | C20: =INDEX(Datos_3J!C40:C46,Datos_3J!$B$6) -> 4.4516129 | D20: =INDEX(Datos_3J!D40:D46,Datos_3J!$B$6) -> 8.4333333
A21: Participación de k en el ingreso mensual | B21: =Terna_Proceso!B7/Terna_Proceso!B9 -> 0.59484373 | C21: =Terna_Proceso!C7/Terna_Proceso!C9 -> 0.215625 | D21: =Terna_Proceso!D7/Terna_Proceso!D9 -> 0.40961489
A22: Ingreso mensual estimado (S/) | B22: =Datos_3J!B69 -> 4860.1 | C22: =Datos_3J!C69 -> 5574.1935 | D22: =Datos_3J!D69 -> 4632.4
A24: Las celdas amarillas con [completar] deben llenarse con la información propia de cada negocio antes de pasar al Word.

Sheet Ventas_Ana
A1: Ventas diarias – Bodega La Esquina de Ana
A4: Estadístico | D4: Aceite | E4: Atún | F4: Gaseosa | G4: Cerveza | H4: Snacks | I4: Azúcar | J4: Leche | K4: Total día
A5: Media | D5: =AVERAGE(D14:D43) -> 1.6 | E5: =AVERAGE(E14:E43) -> 2.3666667 | F5: =AVERAGE(F14:F43) -> 3.0333333 | G5: =AVERAGE(G14:G43) -> 13.766667 | H5: =AVERAGE(H14:H43) -> 3.4666667 | I5: =AVERAGE(I14:I43) -> 1.5 | J5: =AVERAGE(J14:J43) -> 2.2 | K5: =AVERAGE(K14:K43) -> 27.933333
A6: Mediana | D6: =MEDIAN(D14:D43) -> 1.5 | E6: =MEDIAN(E14:E43) -> 2 | F6: =MEDIAN(F14:F43) -> 3 | G6: =MEDIAN(G14:G43) -> 12.5 | H6: =MEDIAN(H14:H43) -> 3 | I6: =MEDIAN(I14:I43) -> 1.5 | J6: =MEDIAN(J14:J43) -> 2 | K6: =MEDIAN(K14:K43) -> 26
A7: Desv. estándar (muestral) | D7: =STDEV(D14:D43) -> 1.1626367 | E7: =STDEV(E14:E43) -> 1.2726116 | F7: =STDEV(F14:F43) -> 2.3116397 | G7: =STDEV(G14:G43) -> 6.8060994 | H7: =STDEV(H14:H43) -> 1.942862 | I7: =STDEV(I14:I43) -> 0.50854763 | J7: =STDEV(J14:J43) -> 0.66436384 | K7: =STDEV(K14:K43) -> 9.3842617
A8: Mínimo | D8: =MIN(D14:D43) -> 0 | E8: =MIN(E14:E43) -> 0 | F8: =MIN(F14:F43) -> 0 | G8: =MIN(G14:G43) -> 3 | H8: =MIN(H14:H43) -> 0 | I8: =MIN(I14:I43) -> 1 | J8: =MIN(J14:J43) -> 1 | K8: =MIN(K14:K43) -> 17
A9: Máximo | D9: =MAX(D14:D43) -> 4 | E9: =MAX(E14:E43) -> 5 | F9: =MAX(F14:F43) -> 11 | G9: =MAX(G14:G43) -> 29 | H9: =MAX(H14:H43) -> 8 | I9: =MAX(I14:I43) -> 2 | J9: =MAX(J14:J43) -> 3 | K9: =MAX(K14:K43) -> 54
A10: Coef. de variación | D10: =IF(D5=0,0,D7/D5) -> 0.72664795 | E10: =IF(E5=0,0,E7/E5) -> 0.5377232 | F10: =IF(F5=0,0,F7/F5) -> 0.76207903 | G10: =IF(G5=0,0,G7/G5) -> 0.49438978 | H10: =IF(H5=0,0,H7/H5) -> 0.56044095 | I10: =IF(I5=0,0,I7/I5) -> 0.33903175 | J10: =IF(J5=0,0,J7/J5) -> 0.30198356 | K10: =IF(K5=0,0,K7/K5) -> 0.33595209
A12: Registro diario
A13: N° día | B13: Fecha | C13: Día | D13: Aceite | E13: Atún | F13: Gaseosa | G13: Cerveza | H13: Snacks | I13: Azúcar | J13: Leche | K13: Total día
A14: 1 | B14: 45836 | C14: =CHOOSE(WEEKDAY(B14,2),"Lun","Mar","Mié","Jue","Vie","Sáb","Dom") -> Sáb | D14: 1 | E14: 2 | F14: 3 | G14: 16 | H14: 5 | I14: 2 | J14: 3 | K14: =SUM(D14:J14) -> 32
A15: 2 | B15: 45837 | C15: =CHOOSE(WEEKDAY(B15,2),"Lun","Mar","Mié","Jue","Vie","Sáb","Dom") -> Dom | D15: 2 | E15: 2 | F15: 7 | G15: 20 | H15: 6 | I15: 1 | J15: 2 | K15: =SUM(D15:J15) -> 40
A16: 3 | B16: 45838 | C16: =CHOOSE(WEEKDAY(B16,2),"Lun","Mar","Mié","Jue","Vie","Sáb","Dom") -> Lun | D16: 3 | E16: 3 | F16: 4 | G16: 7 | H16: 3 | I16: 2 | J16: 1 | K16: =SUM(D16:J16) -> 23
A17: 4 | B17: 45839 | C17: =CHOOSE(WEEKDAY(B17,2),"Lun","Mar","Mié","Jue","Vie","Sáb","Dom") -> Mar | D17: 1 | E17: 1 | F17: 4 | G17: 9 | H17: 5 | I17: 1 | J17: 2 | K17: =SUM(D17:J17) -> 23
A18: 5 | B18: 45840 | C18: =CHOOSE(WEEKDAY(B18,2),"Lun","Mar","Mié","Jue","Vie","Sáb","Dom") -> Mié | D18: 3 | E18: 1 | F18: 2 | G18: 6 | H18: 3 | I18: 2 | J18: 3 | K18: =SUM(D18:J18) -> 20
A19: 6 | B19: 45841 | C19: =CHOOSE(WEEKDAY(B19,2),"Lun","Mar","Mié","Jue","Vie","Sáb","Dom") -> Jue | D19: 2 | E19: 2 | F19: 3 | G19: 11 | H19: 5 | I19: 1 | J19: 2 | K19: =SUM(D19:J19) -> 26
A20: 7 | B20: 45842 | C20: =CHOOSE(WEEKDAY(B20,2),"Lun","Mar","Mié","Jue","Vie","Sáb","Dom") -> Vie | D20: 0 | E20: 2 | F20: 3 | G20: 10 | H20: 1 | I20: 2 | J20: 1 | K20: =SUM(D20:J20) -> 19
A21: 8 | B21: 45843 | C21: =CHOOSE(WEEKDAY(B21,2),"Lun","Mar","Mié","Jue","Vie","Sáb","Dom") -> Sáb | D21: 1 | E21: 3 | F21: 5 | G21: 14 | H21: 2 | I21: 1 | J21: 2 | K21: =SUM(D21:J21) -> 28
A22: 9 | B22: 45844 | C22: =CHOOSE(WEEKDAY(B22,2),"Lun","Mar","Mié","Jue","Vie","Sáb","Dom") -> Dom | D22: 2 | E22: 3 | F22: 11 | G22: 26 | H22: 7 | I22: 2 | J22: 3 | K22: =SUM(D22:J22) -> 54
A23: 10 | B23: 45845 | C23: =CHOOSE(WEEKDAY(B23,2),"Lun","Mar","Mié","Jue","Vie","Sáb","Dom") -> Lun | D23: 1 | E23: 1 | F23: 2 | G23: 12 | H23: 8 | I23: 2 | J23: 2 | K23: =SUM(D23:J23) -> 28
A24: 11 | B24: 45846 | C24: =CHOOSE(WEEKDAY(B24,2),"Lun","Mar","Mié","Jue","Vie","Sáb","Dom") -> Mar | D24: 3 | E24: 2 | F24: 5 | G24: 6 | H24: 4 | I24: 1 | J24: 3 | K24: =SUM(D24:J24) -> 24
A25: 12 | B25: 45847 | C25: =CHOOSE(WEEKDAY(B25,2),"Lun","Mar","Mié","Jue","Vie","Sáb","Dom") -> Mié | D25: 2 | E25: 4 | F25: 3 | G25: 8 | H25: 2 | I25: 2 | J25: 2 | K25: =SUM(D25:J25) -> 23
... A43: 30 | B43: 45865 | C43: =CHOOSE(WEEKDAY(B43,2),"Lun","Mar","Mié","Jue","Vie","Sáb","Dom") -> Dom | D43: 3 | E43: 5 | F43: 5 | G43: 23 | H43: 5 | I43: 1 | J43: 3 | K43: =SUM(D43:J43) -> 45

Sheet Ventas_Berry
A1: Ventas diarias – Berry Blue
A4: Estadístico | D4: Aceite | E4: Atún | F4: Gaseosa | G4: Cerveza | H4: Snacks | I4: Azúcar | J4: Leche | K4: Total día
A5: Media | D5: =AVERAGE(D14:D44) -> 4.483871 | E5: =AVERAGE(E14:E44) -> 4.9354839 | F5: =AVERAGE(F14:F44) -> 2.8064516 | G5: =AVERAGE(G14:G44) -> 4.4516129 | H5: =AVERAGE(H14:H44) -> 4.8387097 | I5: =AVERAGE(I14:I44) -> 4.2258065 | J5: =AVERAGE(J14:J44) -> 4.2580645 | K5: =AVERAGE(K14:K44) -> 30
A6: Mediana | D6: =MEDIAN(D14:D44) -> 4 | E6: =MEDIAN(E14:E44) -> 5 | F6: =MEDIAN(F14:F44) -> 2 | G6: =MEDIAN(G14:G44) -> 4 | H6: =MEDIAN(H14:H44) -> 6 | I6: =MEDIAN(I14:I44) -> 5 | J6: =MEDIAN(J14:J44) -> 4 | K6: =MEDIAN(K14:K44) -> 31
A7: Desv. estándar (muestral) | D7: =STDEV(D14:D44) -> 2.0472904 | E7: =STDEV(E14:E44) -> 2.0483405 | F7: =STDEV(F14:F44) -> 1.9902991 | G7: =STDEV(G14:G44) -> 2.3070719 | H7: =STDEV(H14:H44) -> 2.3818309 | I7: =STDEV(I14:I44) -> 2.2466223 | J7: =STDEV(J14:J44) -> 2.489548 | K7: =STDEV(K14:K44) -> 6.8992753
A8: Mínimo | D8: =MIN(D14:D44) -> 1 | E8: =MIN(E14:E44) -> 1 | F8: =MIN(F14:F44) -> 1 | G8: =MIN(G14:G44) -> 1 | H8: =MIN(H14:H44) -> 1 | I8: =MIN(I14:I44) -> 1 | J8: =MIN(J14:J44) -> 1 | K8: =MIN(K14:K44) -> 18
A9: Máximo | D9: =MAX(D14:D44) -> 8 | E9: =MAX(E14:E44) -> 8 | F9: =MAX(F14:F44) -> 7 | G9: =MAX(G14:G44) -> 8 | H9: =MAX(H14:H44) -> 8 | I9: =MAX(I14:I44) -> 8 | J9: =MAX(J14:J44) -> 8 | K9: =MAX(K14:K44) -> 43
A10: Coef. de variación | D10: =IF(D5=0,0,D7/D5) -> 0.45658994 | E10: =IF(E5=0,0,E7/E5) -> 0.41502324 | F10: =IF(F5=0,0,F7/F5) -> 0.70918702 | G10: =IF(G5=0,0,G7/G5) -> 0.51825528 | H10: =IF(H5=0,0,H7/H5) -> 0.49224505 | I10: =IF(I5=0,0,I7/I5) -> 0.53164345 | J10: =IF(J5=0,0,J7/J5) -> 0.58466659 | K10: =IF(K5=0,0,K7/K5) -> 0.22997584
A12: Registro diario
A13: N° día | B13: Fecha | C13: Día | D13: Aceite | E13: Atún | F13: Gaseosa | G13: Cerveza | H13: Snacks | I13: Azúcar | J13: Leche | K13: Total día
A14: 1 | B14: 46235 | C14: =CHOOSE(WEEKDAY(B14,2),"Lun","Mar","Mié","Jue","Vie","Sáb","Dom") -> Sáb | D14: 2 | E14: 6 | F14: 1 | G14: 4 | H14: 6 | I14: 5 | J14: 7 | K14: =SUM(D14:J14) -> 31
A15: 2 | B15: 46236 | C15: =CHOOSE(WEEKDAY(B15,2),"Lun","Mar","Mié","Jue","Vie","Sáb","Dom") -> Dom | D15: 8 | E15: 3 | F15: 5 | G15: 1 | H15: 1 | I15: 3 | J15: 2 | K15: =SUM(D15:J15) -> 23
A16: 3 | B16: 46237 | C16: =CHOOSE(WEEKDAY(B16,2),"Lun","Mar","Mié","Jue","Vie","Sáb","Dom") -> Lun | D16: 5 | E16: 1 | F16: 6 | G16: 5 | H16: 5 | I16: 6 | J16: 8 | K16: =SUM(D16:J16) -> 36
A17: 4 | B17: 46238 | C17: =CHOOSE(WEEKDAY(B17,2),"Lun","Mar","Mié","Jue","Vie","Sáb","Dom") -> Mar | D17: 4 | E17: 2 | F17: 2 | G17: 5 | H17: 8 | I17: 5 | J17: 1 | K17: =SUM(D17:J17) -> 27
A18: 5 | B18: 46239 | C18: =CHOOSE(WEEKDAY(B18,2),"Lun","Mar","Mié","Jue","Vie","Sáb","Dom") -> Mié | D18: 4 | E18: 5 | F18: 1 | G18: 5 | H18: 1 | I18: 2 | J18: 2 | K18: =SUM(D18:J18) -> 20
A19: 6 | B19: 46240 | C19: =CHOOSE(WEEKDAY(B19,2),"Lun","Mar","Mié","Jue","Vie","Sáb","Dom") -> Jue | D19: 5 | E19: 4 | F19: 2 | G19: 6 | H19: 6 | I19: 5 | J19: 4 | K19: =SUM(D19:J19) -> 32
A20: 7 | B20: 46241 | C20: =CHOOSE(WEEKDAY(B20,2),"Lun","Mar","Mié","Jue","Vie","Sáb","Dom") -> Vie | D20: 8 | E20: 6 | F20: 2 | G20: 5 | H20: 6 | I20: 3 | J20: 4 | K20: =SUM(D20:J20) -> 34
A21: 8 | B21: 46242 | C21: =CHOOSE(WEEKDAY(B21,2),"Lun","Mar","Mié","Jue","Vie","Sáb","Dom") -> Sáb | D21: 8 | E21: 2 | F21: 4 | G21: 1 | H21: 7 | I21: 8 | J21: 8 | K21: =SUM(D21:J21) -> 38
A22: 9 | B22: 46243 | C22: =CHOOSE(WEEKDAY(B22,2),"Lun","Mar","Mié","Jue","Vie","Sáb","Dom") -> Dom | D22: 6 | E22: 5 | F22: 5 | G22: 7 | H22: 5 | I22: 2 | J22: 2 | K22: =SUM(D22:J22) -> 32
A23: 10 | B23: 46244 | C23: =CHOOSE(WEEKDAY(B23,2),"Lun","Mar","Mié","Jue","Vie","Sáb","Dom") -> Lun | D23: 4 | E23: 4 | F23: 1 | G23: 8 | H23: 7 | I23: 1 | J23: 4 | K23: =SUM(D23:J23) -> 29
A24: 11 | B24: 46245 | C24: =CHOOSE(WEEKDAY(B24,2),"Lun","Mar","Mié","Jue","Vie","Sáb","Dom") -> Mar | D24: 4 | E24: 3 | F24: 2 | G24: 4 | H24: 4 | I24: 3 | J24: 4 | K24: =SUM(D24:J24) -> 24
A25: 12 | B25: 46246 | C25: =CHOOSE(WEEKDAY(B25,2),"Lun","Mar","Mié","Jue","Vie","Sáb","Dom") -> Mié | D25: 3 | E25: 4 | F25: 2 | G25: 2 | H25: 7 | I25: 8 | J25: 6 | K25: =SUM(D25:J25) -> 32
... A44: 31 | B44: 46265 | C44: =CHOOSE(WEEKDAY(B44,2),"Lun","Mar","Mié","Jue","Vie","Sáb","Dom") -> Lun | D44: 7 | E44: 6 | F44: 2 | G44: 8 | H44: 6 | I44: 1 | J44: 4 | K44: =SUM(D44:J44) -> 34

Sheet Ventas_Martina
A1: Ventas diarias – Bodega Martina
A4: Estadístico | D4: Aceite | E4: Atún | F4: Gaseosa | G4: Cerveza | H4: Snacks | I4: Azúcar | J4: Leche | K4: Total día
A5: Media | D5: =AVERAGE(D14:D43) -> 2.2666667 | E5: =AVERAGE(E14:E43) -> 3 | F5: =AVERAGE(F14:F43) -> 4.8666667 | G5: =AVERAGE(G14:G43) -> 8.4333333 | H5: =AVERAGE(H14:H43) -> 4.9666667 | I5: =AVERAGE(I14:I43) -> 2.0666667 | J5: =AVERAGE(J14:J43) -> 3.1333333 | K5: =AVERAGE(K14:K43) -> 28.733333
A6: Mediana | D6: =MEDIAN(D14:D43) -> 2 | E6: =MEDIAN(E14:E43) -> 3 | F6: =MEDIAN(F14:F43) -> 4 | G6: =MEDIAN(G14:G43) -> 8 | H6: =MEDIAN(H14:H43) -> 5 | I6: =MEDIAN(I14:I43) -> 2 | J6: =MEDIAN(J14:J43) -> 3 | K6: =MEDIAN(K14:K43) -> 29
A7: Desv. estándar (muestral) | D7: =STDEV(D14:D43) -> 1.2576204 | E7: =STDEV(E14:E43) -> 2 | F7: =STDEV(F14:F43) -> 2.4315928 | G7: =STDEV(G14:G43) -> 3.3598372 | H7: =STDEV(H14:H43) -> 2.3116397 | I7: =STDEV(I14:I43) -> 1.2576204 | J7: =STDEV(J14:J43) -> 1.6760655 | K7: =STDEV(K14:K43) -> 6.6484809
A8: Mínimo | D8: =MIN(D14:D43) -> 0 | E8: =MIN(E14:E43) -> 0 | F8: =MIN(F14:F43) -> 0 | G8: =MIN(G14:G43) -> 2 | H8: =MIN(H14:H43) -> 1 | I8: =MIN(I14:I43) -> 0 | J8: =MIN(J14:J43) -> 1 | K8: =MIN(K14:K43) -> 16
A9: Máximo | D9: =MAX(D14:D43) -> 5 | E9: =MAX(E14:E43) -> 8 | F9: =MAX(F14:F43) -> 10 | G9: =MAX(G14:G43) -> 15 | H9: =MAX(H14:H43) -> 11 | I9: =MAX(I14:I43) -> 5 | J9: =MAX(J14:J43) -> 7 | K9: =MAX(K14:K43) -> 41
A10: Coef. de variación | D10: =IF(D5=0,0,D7/D5) -> 0.55483255 | E10: =IF(E5=0,0,E7/E5) -> 0.66666667 | F10: =IF(F5=0,0,F7/F5) -> 0.49964236 | G10: =IF(G5=0,0,G7/G5) -> 0.39839966 | H10: =IF(H5=0,0,H7/H5) -> 0.46543081 | I10: =IF(I5=0,0,I7/I5) -> 0.60852602 | J10: =IF(J5=0,0,J7/J5) -> 0.53491451 | K10: =IF(K5=0,0,K7/K5) -> 0.23138565
A12: Registro diario
A13: N° día | B13: Fecha | C13: Día | D13: Aceite | E13: Atún | F13: Gaseosa | G13: Cerveza | H13: Snacks | I13: Azúcar | J13: Leche | K13: Total día
A14: 1 | B14: 46266 | C14: =CHOOSE(WEEKDAY(B14,2),"Lun","Mar","Mié","Jue","Vie","Sáb","Dom") -> Mar | D14: 4 | E14: 5 | F14: 3 | G14: 10 | H14: 2 | I14: 0 | J14: 7 | K14: =SUM(D14:J14) -> 31
A15: 2 | B15: 46267 | C15: =CHOOSE(WEEKDAY(B15,2),"Lun","Mar","Mié","Jue","Vie","Sáb","Dom") -> Mié | D15: 2 | E15: 1 | F15: 9 | G15: 6 | H15: 5 | I15: 2 | J15: 1 | K15: =SUM(D15:J15) -> 26
A16: 3 | B16: 46268 | C16: =CHOOSE(WEEKDAY(B16,2),"Lun","Mar","Mié","Jue","Vie","Sáb","Dom") -> Jue | D16: 1 | E16: 3 | F16: 3 | G16: 9 | H16: 4 | I16: 2 | J16: 1 | K16: =SUM(D16:J16) -> 23
A17: 4 | B17: 46269 | C17: =CHOOSE(WEEKDAY(B17,2),"Lun","Mar","Mié","Jue","Vie","Sáb","Dom") -> Vie | D17: 1 | E17: 2 | F17: 4 | G17: 11 | H17: 5 | I17: 3 | J17: 4 | K17: =SUM(D17:J17) -> 30
A18: 5 | B18: 46270 | C18: =CHOOSE(WEEKDAY(B18,2),"Lun","Mar","Mié","Jue","Vie","Sáb","Dom") -> Sáb | D18: 2 | E18: 0 | F18: 8 | G18: 9 | H18: 7 | I18: 1 | J18: 2 | K18: =SUM(D18:J18) -> 29
A19: 6 | B19: 46271 | C19: =CHOOSE(WEEKDAY(B19,2),"Lun","Mar","Mié","Jue","Vie","Sáb","Dom") -> Dom | D19: 2 | E19: 4 | F19: 9 | G19: 13 | H19: 8 | I19: 2 | J19: 3 | K19: =SUM(D19:J19) -> 41
A20: 7 | B20: 46272 | C20: =CHOOSE(WEEKDAY(B20,2),"Lun","Mar","Mié","Jue","Vie","Sáb","Dom") -> Lun | D20: 1 | E20: 3 | F20: 6 | G20: 2 | H20: 3 | I20: 2 | J20: 3 | K20: =SUM(D20:J20) -> 20
A21: 8 | B21: 46273 | C21: =CHOOSE(WEEKDAY(B21,2),"Lun","Mar","Mié","Jue","Vie","Sáb","Dom") -> Mar | D21: 2 | E21: 4 | F21: 3 | G21: 7 | H21: 5 | I21: 2 | J21: 5 | K21: =SUM(D21:J21) -> 28
A22: 9 | B22: 46274 | C22: =CHOOSE(WEEKDAY(B22,2),"Lun","Mar","Mié","Jue","Vie","Sáb","Dom") -> Mié | D22: 2 | E22: 1 | F22: 0 | G22: 10 | H22: 5 | I22: 3 | J22: 3 | K22: =SUM(D22:J22) -> 24
A23: 10 | B23: 46275 | C23: =CHOOSE(WEEKDAY(B23,2),"Lun","Mar","Mié","Jue","Vie","Sáb","Dom") -> Jue | D23: 3 | E23: 7 | F23: 8 | G23: 8 | H23: 3 | I23: 4 | J23: 5 | K23: =SUM(D23:J23) -> 38
A24: 11 | B24: 46276 | C24: =CHOOSE(WEEKDAY(B24,2),"Lun","Mar","Mié","Jue","Vie","Sáb","Dom") -> Vie | D24: 1 | E24: 0 | F24: 4 | G24: 7 | H24: 3 | I24: 2 | J24: 4 | K24: =SUM(D24:J24) -> 21
A25: 12 | B25: 46277 | C25: =CHOOSE(WEEKDAY(B25,2),"Lun","Mar","Mié","Jue","Vie","Sáb","Dom") -> Sáb | D25: 4 | E25: 2 | F25: 6 | G25: 13 | H25: 7 | I25: 3 | J25: 1 | K25: =SUM(D25:J25) -> 36
... A43: 30 | B43: 46295 | C43: =CHOOSE(WEEKDAY(B43,2),"Lun","Mar","Mié","Jue","Vie","Sáb","Dom") -> Mié | D43: 3 | E43: 3 | F43: 4 | G43: 8 | H43: 6 | I43: 5 | J43: 2 | K43: =SUM(D43:J43) -> 31

Sheet Datos_3J
A1: Datos cuantitativos – Matriz de 3 jugadores
A2: Precios, costos, volumen medio diario, volumen mensual e ingreso mensual por empresa y producto.
A4: Días por mes | B4: 30 | D4: Celdas azules = datos editables. Cambiar B5 recalcula todo el libro con otro producto en disputa.
A5: Producto en disputa (k) | B5: Cerveza
A6: Posición de k en la lista | B6: =MATCH(B5,A10:A16,0) -> 4
A8: 1. Precio de venta unitario (S/ por unidad)
A9: Producto | B9: Ana | C9: Berry | D9: Martina | E9: Presentación de referencia
A10: Aceite | B10: 10.5 | C10: 11 | D10: 10.5 | E10: Aceite vegetal 1 L (Primor / Cocinero)
A11: Atún | B11: 6 | C11: 6.5 | D11: 6.2 | E11: Atún en filete 170 g (Florida / Campomar)
A12: Gaseosa | B12: 3 | C12: 3.5 | D12: 2.8 | E12: Gaseosa personal 500 ml (Guaraná / Coca-Cola)
A13: Cerveza | B13: 7 | C13: 9 | D13: 7.5 | E13: Cerveza 620 ml (Cristal / Pilsen)
A14: Snacks | B14: 2.5 | C14: 2.5 | D14: 2.3 | E14: Snack 35–40 g (Lay's / Piqueo)
A15: Azúcar | B15: 4.5 | C15: 5 | D15: 4.5 | E15: Azúcar rubia 1 kg (Paramonga / Cartavio)
A16: Leche | B16: 4.6 | C16: 5 | D16: 4.6 | E16: Leche evaporada 400 g (Gloria)
A18: 2. Costo unitario de compra (S/ por unidad)
A19: Producto | B19: Ana | C19: Berry | D19: Martina
A20: Aceite | B20: 8.9 | C20: 9.3 | D20: 8.8
A21: Atún | B21: 4.9 | C21: 5.3 | D21: 5
A22: Gaseosa | B22: 2.4 | C22: 2.7 | D22: 2.25
A23: Cerveza | B23: 5.5 | C23: 6.3 | D23: 5.7
A24: Snacks | B24: 1.95 | C24: 1.95 | D24: 1.8
A25: Azúcar | B25: 3.8 | C25: 4.1 | D25: 3.75
A26: Leche | B26: 3.85 | C26: 4.05 | D26: 3.85
A28: 3. Margen unitario (S/) = precio − costo
A29: Producto | B29: Ana | C29: Berry | D29: Martina
A30: Aceite | B30: =B10-B20 -> 1.6 | C30: =C10-C20 -> 1.7 | D30: =D10-D20 -> 1.7
A31: Atún | B31: =B11-B21 -> 1.1 | C31: =C11-C21 -> 1.2 | D31: =D11-D21 -> 1.2
A32: Gaseosa | B32: =B12-B22 -> 0.6 | C32: =C12-C22 -> 0.8 | D32: =D12-D22 -> 0.55
A33: Cerveza | B33: =B13-B23 -> 1.5 | C33: =C13-C23 -> 2.7 | D33: =D13-D23 -> 1.8
A34: Snacks | B34: =B14-B24 -> 0.55 | C34: =C14-C24 -> 0.55 | D34: =D14-D24 -> 0.5
A35: Azúcar | B35: =B15-B25 -> 0.7 | C35: =C15-C25 -> 0.9 | D35: =D15-D25 -> 0.75
A36: Leche | B36: =B16-B26 -> 0.75 | C36: =C16-C26 -> 0.95 | D36: =D16-D26 -> 0.75
A38: 4. Volumen medio diario (unidades/día) – vinculado a las hojas Ventas_*
A39: Producto | B39: Ana | C39: Berry | D39: Martina | E39: Total
A40: Aceite | B40: =Ventas_Ana!D5 -> 1.6 | C40: =Ventas_Berry!D5 -> 4.483871 | D40: =Ventas_Martina!D5 -> 2.2666667 | E40: =SUM(B40:D40) -> 8.3505376
A41: Atún | B41: =Ventas_Ana!E5 -> 2.3666667 | C41: =Ventas_Berry!E5 -> 4.9354839 | D41: =Ventas_Martina!E5 -> 3 | E41: =SUM(B41:D41) -> 10.302151
A42: Gaseosa | B42: =Ventas_Ana!F5 -> 3.0333333 | C42: =Ventas_Berry!F5 -> 2.8064516 | D42: =Ventas_Martina!F5 -> 4.8666667 | E42: =SUM(B42:D42) -> 10.706452
A43: Cerveza | B43: =Ventas_Ana!G5 -> 13.766667 | C43: =Ventas_Berry!G5 -> 4.4516129 | D43: =Ventas_Martina!G5 -> 8.4333333 | E43: =SUM(B43:D43) -> 26.651613
A44: Snacks | B44: =Ventas_Ana!H5 -> 3.4666667 | C44: =Ventas_Berry!H5 -> 4.8387097 | D44: =Ventas_Martina!H5 -> 4.9666667 | E44: =SUM(B44:D44) -> 13.272043
A45: Azúcar | B45: =Ventas_Ana!I5 -> 1.5 | C45: =Ventas_Berry!I5 -> 4.2258065 | D45: =Ventas_Martina!I5 -> 2.0666667 | E45: =SUM(B45:D45) -> 7.7924731
A46: Leche | B46: =Ventas_Ana!J5 -> 2.2 | C46: =Ventas_Berry!J5 -> 4.2580645 | D46: =Ventas_Martina!J5 -> 3.1333333 | E46: =SUM(B46:D46) -> 9.5913978
A47: Total | B47: =SUM(B40:B46) -> 27.933333 | C47: =SUM(C40:C46) -> 30 | D47: =SUM(D40:D46) -> 28.733333 | E47: =SUM(E40:E46) -> 86.666667
A49: 5. Volumen mensual (unidades) = media diaria × días por mes
A50: Producto | B50: Ana | C50: Berry | D50: Martina | E50: Total
A51: Aceite | B51: =B40*$B$4 -> 48 | C51: =C40*$B$4 -> 134.51613 | D51: =D40*$B$4 -> 68 | E51: =SUM(B51:D51) -> 250.51613
A52: Atún | B52: =B41*$B$4 -> 71 | C52: =C41*$B$4 -> 148.06452 | D52: =D41*$B$4 -> 90 | E52: =SUM(B52:D52) -> 309.06452
A53: Gaseosa | B53: =B42*$B$4 -> 91 | C53: =C42*$B$4 -> 84.193548 | D53: =D42*$B$4 -> 146 | E53: =SUM(B53:D53) -> 321.19355
A54: Cerveza | B54: =B43*$B$4 -> 413 | C54: =C43*$B$4 -> 133.54839 | D54: =D43*$B$4 -> 253 | E54: =SUM(B54:D54) -> 799.54839
A55: Snacks | B55: =B44*$B$4 -> 104 | C55: =C44*$B$4 -> 145.16129 | D55: =D44*$B$4 -> 149 | E55: =SUM(B55:D55) -> 398.16129
A56: Azúcar | B56: =B45*$B$4 -> 45 | C56: =C45*$B$4 -> 126.77419 | D56: =D45*$B$4 -> 62 | E56: =SUM(B56:D56) -> 233.77419
A57: Leche | B57: =B46*$B$4 -> 66 | C57: =C46*$B$4 -> 127.74194 | D57: =D46*$B$4 -> 94 | E57: =SUM(B57:D57) -> 287.74194
A58: Total | B58: =SUM(B51:B57) -> 838 | C58: =SUM(C51:C57) -> 900 | D58: =SUM(D51:D57) -> 862 | E58: =SUM(E51:E57) -> 2600
A60: 6. Ingreso mensual (S/) = volumen mensual × precio
A61: Producto | B61: Ana | C61: Berry | D61: Martina | E61: Total
A62: Aceite | B62: =B51*B10 -> 504 | C62: =C51*C10 -> 1479.6774 | D62: =D51*D10 -> 714 | E62: =SUM(B62:D62) -> 2697.6774
A63: Atún | B63: =B52*B11 -> 426 | C63: =C52*C11 -> 962.41935 | D63: =D52*D11 -> 558 | E63: =SUM(B63:D63) -> 1946.4194
A64: Gaseosa | B64: =B53*B12 -> 273 | C64: =C53*C12 -> 294.67742 | D64: =D53*D12 -> 408.8 | E64: =SUM(B64:D64) -> 976.47742
A65: Cerveza | B65: =B54*B13 -> 2891 | C65: =C54*C13 -> 1201.9355 | D65: =D54*D13 -> 1897.5 | E65: =SUM(B65:D65) -> 5990.4355
A66: Snacks | B66: =B55*B14 -> 260 | C66: =C55*C14 -> 362.90323 | D66: =D55*D14 -> 342.7 | E66: =SUM(B66:D66) -> 965.60323
A67: Azúcar | B67: =B56*B15 -> 202.5 | C67: =C56*C15 -> 633.87097 | D67: =D56*D15 -> 279 | E67: =SUM(B67:D67) -> 1115.371
A68: Leche | B68: =B57*B16 -> 303.6 | C68: =C57*C16 -> 638.70968 | D68: =D57*D16 -> 432.4 | E68: =SUM(B68:D68) -> 1374.7097
A69: Total | B69: =SUM(B62:B68) -> 4860.1 | C69: =SUM(C62:C68) -> 5574.1935 | D69: =SUM(D62:D68) -> 4632.4 | E69: =SUM(E62:E68) -> 15066.694
A71: Precios y costos: valores de referencia de mercado minorista (S/ por unidad); son supuestos editables, no cifras de un tercero. Volúmenes: datos diarios de cada negocio (hojas Ventas_*).

Sheet Terna_Proceso
A1: Proceso de generación de cada terna (3 jugadores)
A2: Juego: cada empresa decide si OFRECE o NO el producto en disputa (k). Si una sale, su venta de k se reparte entre las que sí ofrecen, según su participación.
A3: Producto en disputa (k): | B3: =Datos_3J!B5 -> Cerveza
A5: Paso 1 – Ingreso mensual (S/): producto k vs. resto de productos
A6: Concepto | B6: Ana | C6: Berry | D6: Martina | E6: Total
A7: Ingreso en k (Rk) | B7: =INDEX(Datos_3J!B62:B68,Datos_3J!$B$6) -> 2891 | C7: =INDEX(Datos_3J!C62:C68,Datos_3J!$B$6) -> 1201.9355 | D7: =INDEX(Datos_3J!D62:D68,Datos_3J!$B$6) -> 1897.5 | E7: =SUM(B7:D7) -> 5990.4355
A8: Ingreso en el resto de productos (Ro) | B8: =Datos_3J!B69-B7 -> 1969.1 | C8: =Datos_3J!C69-C7 -> 4372.2581 | D8: =Datos_3J!D69-D7 -> 2734.9 | E8: =SUM(B8:D8) -> 9076.2581
A9: Ingreso total (todos ofrecen) | B9: =B7+B8 -> 4860.1 | C9: =C7+C8 -> 5574.1935 | D9: =D7+D8 -> 4632.4 | E9: =SUM(B9:D9) -> 15066.694
A10: Participación en k | B10: =B7/$E$7 -> 0.48260264 | C10: =C7/$E$7 -> 0.20064242 | D10: =D7/$E$7 -> 0.31675493 | E10: =SUM(B10:D10) -> 1
A12: Paso 2 – Participación en k cuando una empresa NO ofrece (se reparte entre las que quedan)
A13: Escenario | B13: Ana | C13: Berry | D13: Martina | E13: Suma
A14: Todos ofrecen | B14: =B10 -> 0.48260264 | C14: =C10 -> 0.20064242 | D14: =D10 -> 0.31675493 | E14: =SUM(B14:D14) -> 1
A15: Ana NO ofrece | B15: =0 -> 0 | C15: =C$7/($E$7-$B$7) -> 0.38779174 | D15: =D$7/($E$7-$B$7) -> 0.61220826 | E15: =SUM(B15:D15) -> 1
A16: Berry NO ofrece | B16: =B$7/($E$7-$C$7) -> 0.60373812 | C16: =0 -> 0 | D16: =D$7/($E$7-$C$7) -> 0.39626188 | E16: =SUM(B16:D16) -> 1
A17: Martina NO ofrece | B17: =B$7/($E$7-$D$7) -> 0.70633901 | C17: =C$7/($E$7-$D$7) -> 0.29366099 | D17: =0 -> 0 | E17: =SUM(B17:D17) -> 1
A19: Paso 3 – Reparto (S/) del ingreso en k de la empresa que sale
A20: Escenario | B20: Ana | C20: Berry | D20: Martina | E20: Suma (= Rk de quien sale)
A21: Ana NO ofrece | B21: =$B$7*B15 -> 0 | C21: =$B$7*C15 -> 1121.1059 | D21: =$B$7*D15 -> 1769.8941 | E21: =SUM(B21:D21) -> 2891
A22: Berry NO ofrece | B22: =$C$7*B16 -> 725.65427 | C22: =$C$7*C16 -> 0 | D22: =$C$7*D16 -> 476.28121 | E22: =SUM(B22:D22) -> 1201.9355
A23: Martina NO ofrece | B23: =$D$7*B17 -> 1340.2783 | C23: =$D$7*C17 -> 557.22173 | D23: =$D$7*D17 -> 0 | E23: =SUM(B23:D23) -> 1897.5
A24: Lectura: la fila de cada escenario muestra a quién se le transfiere la venta de k de la empresa que sale (la propia empresa recibe 0).
A25: Paso 4 – Las 8 ternas: ingreso original (V) y pago suma nula (u = V − base media)
A26: Perfil (decisiones) | B26: Ana (1=ofrece) | C26: Berry | D26: Martina | E26: Clave | F26: S = Σ Rk de quienes ofrecen | G26: Pool = Rk de quienes salen | H26: V Ana | I26: V Berry | J26: V Martina | K26: Total | L26: Base media | M26: u Ana | N26: u Berry | O26: u Martina | P26: Control Σu=0 | Q26: Terna suma nula (Ana; Berry; Martina) | R26: u Ana si cambia | S26: u Berry si cambia | T26: u Martina si cambia | U26: ¿Ana mejor resp.? | V26: ¿Berry mejor resp.? | W26: ¿Martina mejor resp.? | X26: Equilibrio de Nash
A27: ="Ana "&IF(B27=1,"ofrece","NO ofrece")&" | Berry "&IF(C27=1,"ofrece","NO ofrece")&" | Martina "&IF(D27=1,"ofrece","NO ofrece") -> Ana ofrece | Berry ofrece | Martina ofrece | B27: 1 | C27: 1 | D27: 1 | E27: =B27&C27&D27 -> 111 | F27: =B27*$B$7+C27*$C$7+D27*$D$7 -> 5990.4355 | G27: =(1-B27)*$B$7+(1-C27)*$C$7+(1-D27)*$D$7 -> 0 | H27: =B27*($B$7+IF($F27>0,$G27*$B$7/$F27,0))+$B$8 -> 4860.1 | I27: =C27*($C$7+IF($F27>0,$G27*$C$7/$F27,0))+$C$8 -> 5574.1935 | J27: =D27*($D$7+IF($F27>0,$G27*$D$7/$F27,0))+$D$8 -> 4632.4 | K27: =SUM(H27:J27) -> 15066.694 | L27: =K27/3 -> 5022.2312 | M27: =H27-$L27 -> -162.13118 | N27: =I27-$L27 -> 551.96237 | O27: =J27-$L27 -> -389.83118 | P27: =ROUND(SUM(M27:O27),4) -> 0 | Q27: ="("&TEXT(M27,"#,##0;-#,##0")&"; "&TEXT(N27,"#,##0;-#,##0")&"; "&TEXT(O27,"#,##0;-#,##0")&")" -> (-162; 552; -390) | R27: =INDEX(M$27:M$34,MATCH((1-B27)&C27&D27,$E$27:$E$34,0)) -> -3053.1312 | S27: =INDEX(N$27:N$34,MATCH(B27&(1-C27)&D27,$E$27:$E$34,0)) -> -649.97312 | T27: =INDEX(O$27:O$34,MATCH(B27&C27&(1-D27),$E$27:$E$34,0)) -> -2287.3312 | U27: =IF(M27>=R27,1,0) -> 1 | V27: =IF(N27>=S27,1,0) -> 1 | W27: =IF(O27>=T27,1,0) -> 1 | X27: =IF(U27*V27*W27=1,"NASH","") -> NASH
A28: ="Ana "&IF(B28=1,"ofrece","NO ofrece")&" | Berry "&IF(C28=1,"ofrece","NO ofrece")&" | Martina "&IF(D28=1,"ofrece","NO ofrece") -> Ana ofrece | Berry ofrece | Martina NO ofrece | B28: 1 | C28: 1 | D28: 0 | E28: =B28&C28&D28 -> 110 | F28: =B28*$B$7+C28*$C$7+D28*$D$7 -> 4092.9355 | G28: =(1-B28)*$B$7+(1-C28)*$C$7+(1-D28)*$D$7 -> 1897.5 | H28: =B28*($B$7+IF($F28>0,$G28*$B$7/$F28,0))+$B$8 -> 6200.3783 | I28: =C28*($C$7+IF($F28>0,$G28*$C$7/$F28,0))+$C$8 -> 6131.4153 | J28: =D28*($D$7+IF($F28>0,$G28*$D$7/$F28,0))+$D$8 -> 2734.9 | K28: =SUM(H28:J28) -> 15066.694 | L28: =K28/3 -> 5022.2312 | M28: =H28-$L28 -> 1178.1471 | N28: =I28-$L28 -> 1109.1841 | O28: =J28-$L28 -> -2287.3312 | P28: =ROUND(SUM(M28:O28),4) -> 0 | Q28: ="("&TEXT(M28,"#,##0;-#,##0")&"; "&TEXT(N28,"#,##0;-#,##0")&"; "&TEXT(O28,"#,##0;-#,##0")&")" -> (1,178; 1,109; -2,287) | R28: =INDEX(M$27:M$34,MATCH((1-B28)&C28&D28,$E$27:$E$34,0)) -> -3053.1312 | S28: =INDEX(N$27:N$34,MATCH(B28&(1-C28)&D28,$E$27:$E$34,0)) -> -649.97312 | T28: =INDEX(O$27:O$34,MATCH(B28&C28&(1-D28),$E$27:$E$34,0)) -> -389.83118 | U28: =IF(M28>=R28,1,0) -> 1 | V28: =IF(N28>=S28,1,0) -> 1 | W28: =IF(O28>=T28,1,0) -> 0 | X28: =IF(U28*V28*W28=1,"NASH","")
A29: ="Ana "&IF(B29=1,"ofrece","NO ofrece")&" | Berry "&IF(C29=1,"ofrece","NO ofrece")&" | Martina "&IF(D29=1,"ofrece","NO ofrece") -> Ana ofrece | Berry NO ofrece | Martina ofrece | B29: 1 | C29: 0 | D29: 1 | E29: =B29&C29&D29 -> 101 | F29: =B29*$B$7+C29*$C$7+D29*$D$7 -> 4788.5 | G29: =(1-B29)*$B$7+(1-C29)*$C$7+(1-D29)*$D$7 -> 1201.9355 | H29: =B29*($B$7+IF($F29>0,$G29*$B$7/$F29,0))+$B$8 -> 5585.7543 | I29: =C29*($C$7+IF($F29>0,$G29*$C$7/$F29,0))+$C$8 -> 4372.2581 | J29: =D29*($D$7+IF($F29>0,$G29*$D$7/$F29,0))+$D$8 -> 5108.6812 | K29: =SUM(H29:J29) -> 15066.694 | L29: =K29/3 -> 5022.2312 | M29: =H29-$L29 -> 563.52309 | N29: =I29-$L29 -> -649.97312 | O29: =J29-$L29 -> 86.450029 | P29: =ROUND(SUM(M29:O29),4) -> 0 | Q29: ="("&TEXT(M29,"#,##0;-#,##0")&"; "&TEXT(N29,"#,##0;-#,##0")&"; "&TEXT(O29,"#,##0;-#,##0")&")" -> (564; -650; 86) | R29: =INDEX(M$27:M$34,MATCH((1-B29)&C29&D29,$E$27:$E$34,0)) -> -3053.1312 | S29: =INDEX(N$27:N$34,MATCH(B29&(1-C29)&D29,$E$27:$E$34,0)) -> 551.96237 | T29: =INDEX(O$27:O$34,MATCH(B29&C29&(1-D29),$E$27:$E$34,0)) -> -2287.3312 | U29: =IF(M29>=R29,1,0) -> 1 | V29: =IF(N29>=S29,1,0) -> 0 | W29: =IF(O29>=T29,1,0) -> 1 | X29: =IF(U29*V29*W29=1,"NASH","")
A30: ="Ana "&IF(B30=1,"ofrece","NO ofrece")&" | Berry "&IF(C30=1,"ofrece","NO ofrece")&" | Martina "&IF(D30=1,"ofrece","NO ofrece") -> Ana ofrece | Berry NO ofrece | Martina NO ofrece | B30: 1 | C30: 0 | D30: 0 | E30: =B30&C30&D30 -> 100 | F30: =B30*$B$7+C30*$C$7+D30*$D$7 -> 2891 | G30: =(1-B30)*$B$7+(1-C30)*$C$7+(1-D30)*$D$7 -> 3099.4355 | H30: =B30*($B$7+IF($F30>0,$G30*$B$7/$F30,0))+$B$8 -> 7959.5355 | I30: =C30*($C$7+IF($F30>0,$G30*$C$7/$F30,0))+$C$8 -> 4372.2581 | J30: =D30*($D$7+IF($F30>0,$G30*$D$7/$F30,0))+$D$8 -> 2734.9 | K30: =SUM(H30:J30) -> 15066.694 | L30: =K30/3 -> 5022.2312 | M30: =H30-$L30 -> 2937.3043 | N30: =I30-$L30 -> -649.97312 | O30: =J30-$L30 -> -2287.3312 | P30: =ROUND(SUM(M30:O30),4) -> 0 | Q30: ="("&TEXT(M30,"#,##0;-#,##0")&"; "&TEXT(N30,"#,##0;-#,##0")&"; "&TEXT(O30,"#,##0;-#,##0")&")" -> (2,937; -650; -2,287) | R30: =INDEX(M$27:M$34,MATCH((1-B30)&C30&D30,$E$27:$E$34,0)) -> -1056.3194 | S30: =INDEX(N$27:N$34,MATCH(B30&(1-C30)&D30,$E$27:$E$34,0)) -> 1109.1841 | T30: =INDEX(O$27:O$34,MATCH(B30&C30&(1-D30),$E$27:$E$34,0)) -> 86.450029 | U30: =IF(M30>=R30,1,0) -> 1 | V30: =IF(N30>=S30,1,0) -> 0 | W30: =IF(O30>=T30,1,0) -> 0 | X30: =IF(U30*V30*W30=1,"NASH","")
A31: ="Ana "&IF(B31=1,"ofrece","NO ofrece")&" | Berry "&IF(C31=1,"ofrece","NO ofrece")&" | Martina "&IF(D31=1,"ofrece","NO ofrece") -> Ana NO ofrece | Berry ofrece | Martina ofrece | B31: 0 | C31: 1 | D31: 1 | E31: =B31&C31&D31 -> 011 | F31: =B31*$B$7+C31*$C$7+D31*$D$7 -> 3099.4355 | G31: =(1-B31)*$B$7+(1-C31)*$C$7+(1-D31)*$D$7 -> 2891 | H31: =B31*($B$7+IF($F31>0,$G31*$B$7/$F31,0))+$B$8 -> 1969.1 | I31: =C31*($C$7+IF($F31>0,$G31*$C$7/$F31,0))+$C$8 -> 6695.2995 | J31: =D31*($D$7+IF($F31>0,$G31*$D$7/$F31,0))+$D$8 -> 6402.2941 | K31: =SUM(H31:J31) -> 15066.694 | L31: =K31/3 -> 5022.2312 | M31: =H31-$L31 -> -3053.1312 | N31: =I31-$L31 -> 1673.0683 | O31: =J31-$L31 -> 1380.0629 | P31: =ROUND(SUM(M31:O31),4) -> 0 | Q31: ="("&TEXT(M31,"#,##0;-#,##0")&"; "&TEXT(N31,"#,##0;-#,##0")&"; "&TEXT(O31,"#,##0;-#,##0")&")" -> (-3,053; 1,673; 1,380) | R31: =INDEX(M$27:M$34,MATCH((1-B31)&C31&D31,$E$27:$E$34,0)) -> -162.13118 | S31: =INDEX(N$27:N$34,MATCH(B31&(1-C31)&D31,$E$27:$E$34,0)) -> -649.97312 | T31: =INDEX(O$27:O$34,MATCH(B31&C31&(1-D31),$E$27:$E$34,0)) -> -2287.3312 | U31: =IF(M31>=R31,1,0) -> 0 | V31: =IF(N31>=S31,1,0) -> 1 | W31: =IF(O31>=T31,1,0) -> 1 | X31: =IF(U31*V31*W31=1,"NASH","")
A32: ="Ana "&IF(B32=1,"ofrece","NO ofrece")&" | Berry "&IF(C32=1,"ofrece","NO ofrece")&" | Martina "&IF(D32=1,"ofrece","NO ofrece") -> Ana NO ofrece | Berry ofrece | Martina NO ofrece | B32: 0 | C32: 1 | D32: 0 | E32: =B32&C32&D32 -> 010 | F32: =B32*$B$7+C32*$C$7+D32*$D$7 -> 1201.9355 | G32: =(1-B32)*$B$7+(1-C32)*$C$7+(1-D32)*$D$7 -> 4788.5 | H32: =B32*($B$7+IF($F32>0,$G32*$B$7/$F32,0))+$B$8 -> 1969.1 | I32: =C32*($C$7+IF($F32>0,$G32*$C$7/$F32,0))+$C$8 -> 10362.694 | J32: =D32*($D$7+IF($F32>0,$G32*$D$7/$F32,0))+$D$8 -> 2734.9 | K32: =SUM(H32:J32) -> 15066.694 | L32: =K32/3 -> 5022.2312 | M32: =H32-$L32 -> -3053.1312 | N32: =I32-$L32 -> 5340.4624 | O32: =J32-$L32 -> -2287.3312 | P32: =ROUND(SUM(M32:O32),4) -> 0 | Q32: ="("&TEXT(M32,"#,##0;-#,##0")&"; "&TEXT(N32,"#,##0;-#,##0")&"; "&TEXT(O32,"#,##0;-#,##0")&")" -> (-3,053; 5,340; -2,287) | R32: =INDEX(M$27:M$34,MATCH((1-B32)&C32&D32,$E$27:$E$34,0)) -> 1178.1471 | S32: =INDEX(N$27:N$34,MATCH(B32&(1-C32)&D32,$E$27:$E$34,0)) -> 1346.8387 | T32: =INDEX(O$27:O$34,MATCH(B32&C32&(1-D32),$E$27:$E$34,0)) -> 1380.0629 | U32: =IF(M32>=R32,1,0) -> 0 | V32: =IF(N32>=S32,1,0) -> 1 | W32: =IF(O32>=T32,1,0) -> 0 | X32: =IF(U32*V32*W32=1,"NASH","")
A33: ="Ana "&IF(B33=1,"ofrece","NO ofrece")&" | Berry "&IF(C33=1,"ofrece","NO ofrece")&" | Martina "&IF(D33=1,"ofrece","NO ofrece") -> Ana NO ofrece | Berry NO ofrece | Martina ofrece | B33: 0 | C33: 0 | D33: 1 | E33: =B33&C33&D33 -> 001 | F33: =B33*$B$7+C33*$C$7+D33*$D$7 -> 1897.5 | G33: =(1-B33)*$B$7+(1-C33)*$C$7+(1-D33)*$D$7 -> 4092.9355 | H33: =B33*($B$7+IF($F33>0,$G33*$B$7/$F33,0))+$B$8 -> 1969.1 | I33: =C33*($C$7+IF($F33>0,$G33*$C$7/$F33,0))+$C$8 -> 4372.2581 | J33: =D33*($D$7+IF($F33>0,$G33*$D$7/$F33,0))+$D$8 -> 8725.3355 | K33: =SUM(H33:J33) -> 15066.694 | L33: =K33/3 -> 5022.2312 | M33: =H33-$L33 -> -3053.1312 | N33: =I33-$L33 -> -649.97312 | O33: =J33-$L33 -> 3703.1043 | P33: =ROUND(SUM(M33:O33),4) -> 0 | Q33: ="("&TEXT(M33,"#,##0;-#,##0")&"; "&TEXT(N33,"#,##0;-#,##0")&"; "&TEXT(O33,"#,##0;-#,##0")&")" -> (-3,053; -650; 3,703) | R33: =INDEX(M$27:M$34,MATCH((1-B33)&C33&D33,$E$27:$E$34,0)) -> 563.52309 | S33: =INDEX(N$27:N$34,MATCH(B33&(1-C33)&D33,$E$27:$E$34,0)) -> 1673.0683 | T33: =INDEX(O$27:O$34,MATCH(B33&C33&(1-D33),$E$27:$E$34,0)) -> -290.51935 | U33: =IF(M33>=R33,1,0) -> 0 | V33: =IF(N33>=S33,1,0) -> 0 | W33: =IF(O33>=T33,1,0) -> 1 | X33: =IF(U33*V33*W33=1,"NASH","")
A34: ="Ana "&IF(B34=1,"ofrece","NO ofrece")&" | Berry "&IF(C34=1,"ofrece","NO ofrece")&" | Martina "&IF(D34=1,"ofrece","NO ofrece") -> Ana NO ofrece | Berry NO ofrece | Martina NO ofrece | B34: 0 | C34: 0 | D34: 0 | E34: =B34&C34&D34 -> 000 | F34: =B34*$B$7+C34*$C$7+D34*$D$7 -> 0 | G34: =(1-B34)*$B$7+(1-C34)*$C$7+(1-D34)*$D$7 -> 5990.4355 | H34: =B34*($B$7+IF($F34>0,$G34*$B$7/$F34,0))+$B$8 -> 1969.1 | I34: =C34*($C$7+IF($F34>0,$G34*$C$7/$F34,0))+$C$8 -> 4372.2581 | J34: =D34*($D$7+IF($F34>0,$G34*$D$7/$F34,0))+$D$8 -> 2734.9 | K34: =SUM(H34:J34) -> 9076.2581 | L34: =K34/3 -> 3025.4194 | M34: =H34-$L34 -> -1056.3194 | N34: =I34-$L34 -> 1346.8387 | O34: =J34-$L34 -> -290.51935 | P34: =ROUND(SUM(M34:O34),4) -> 0 | Q34: ="("&TEXT(M34,"#,##0;-#,##0")&"; "&TEXT(N34,"#,##0;-#,##0")&"; "&TEXT(O34,"#,##0;-#,##0")&")" -> (-1,056; 1,347; -291) | R34: =INDEX(M$27:M$34,MATCH((1-B34)&C34&D34,$E$27:$E$34,0)) -> 2937.3043 | S34: =INDEX(N$27:N$34,MATCH(B34&(1-C34)&D34,$E$27:$E$34,0)) -> 5340.4624 | T34: =INDEX(O$27:O$34,MATCH(B34&C34&(1-D34),$E$27:$E$34,0)) -> 3703.1043 | U34: =IF(M34>=R34,1,0) -> 0 | V34: =IF(N34>=S34,1,0) -> 0 | W34: =IF(O34>=T34,1,0) -> 0 | X34: =IF(U34*V34*W34=1,"NASH","")
A36: Fórmula del pago original: V_i = f_i · ( Rk_i + Pool · Rk_i / S ) + Ro_i → si la empresa i no ofrece (f_i = 0) pierde su Rk y conserva Ro; si ofrece, recibe además su cuota (Rk_i/S) del pool de las que salieron. Base media = Total/3 y u_i = V_i − Base media, de modo que Σu = 0 (suma nula). Cuando nadie ofrece (S = 0) no hay a quién transferir y la base media se calcula con el total de esa terna.
A37: Nash: ninguna empresa gana cambiando sola su decisión (columnas U–W = 1 para las tres). Se compara el pago actual con el pago de la terna vecina (clave con ese dígito invertido).

Sheet Matriz_3J
A1: Matriz de pagos de 3 jugadores – suma nula
A2: J1 = Ana (filas) · J2 = Berry (columnas) · J3 = Martina (bloque). Cada celda es una terna (u Ana; u Berry; u Martina) en S/ por mes respecto a la base media.
A3: Producto en disputa (k): | B3: =Datos_3J!B5 -> Cerveza
A5: A. Matriz ORIGINAL – ingreso mensual V (S/) de cada empresa
A7: J3: Martina OFRECE
B8: J2: Berry OFRECE | D8: J2: Berry NO OFRECE
A9: J1: Ana OFRECE | B9: ="("&TEXT(INDEX(Terna_Proceso!H$27:H$34,MATCH("111",Terna_Proceso!$E$27:$E$34,0)),"#,##0")&"; "&TEXT(INDEX(Terna_Proceso!I$27:I$34,MATCH("111",Terna_Proceso!$E$27:$E$34,0)),"#,##0")&"; "&TEXT(INDEX(Terna_Proceso!J$27:J$34,MATCH("111",Terna_Proceso!$E$27:$E$34,0)),"#,##0")&")" -> (4,860; 5,574; 4,632) | D9: ="("&TEXT(INDEX(Terna_Proceso!H$27:H$34,MATCH("101",Terna_Proceso!$E$27:$E$34,0)),"#,##0")&"; "&TEXT(INDEX(Terna_Proceso!I$27:I$34,MATCH("101",Terna_Proceso!$E$27:$E$34,0)),"#,##0")&"; "&TEXT(INDEX(Terna_Proceso!J$27:J$34,MATCH("101",Terna_Proceso!$E$27:$E$34,0)),"#,##0")&")" -> (5,586; 4,372; 5,109)
A10: J1: Ana NO OFRECE | B10: ="("&TEXT(INDEX(Terna_Proceso!H$27:H$34,MATCH("011",Terna_Proceso!$E$27:$E$34,0)),"#,##0")&"; "&TEXT(INDEX(Terna_Proceso!I$27:I$34,MATCH("011",Terna_Proceso!$E$27:$E$34,0)),"#,##0")&"; "&TEXT(INDEX(Terna_Proceso!J$27:J$34,MATCH("011",Terna_Proceso!$E$27:$E$34,0)),"#,##0")&")" -> (1,969; 6,695; 6,402) | D10: ="("&TEXT(INDEX(Terna_Proceso!H$27:H$34,MATCH("001",Terna_Proceso!$E$27:$E$34,0)),"#,##0")&"; "&TEXT(INDEX(Terna_Proceso!I$27:I$34,MATCH("001",Terna_Proceso!$E$27:$E$34,0)),"#,##0")&"; "&TEXT(INDEX(Terna_Proceso!J$27:J$34,MATCH("001",Terna_Proceso!$E$27:$E$34,0)),"#,##0")&")" -> (1,969; 4,372; 8,725)
A13: J3: Martina NO OFRECE
B14: J2: Berry OFRECE | D14: J2: Berry NO OFRECE
A15: J1: Ana OFRECE | B15: ="("&TEXT(INDEX(Terna_Proceso!H$27:H$34,MATCH("110",Terna_Proceso!$E$27:$E$34,0)),"#,##0")&"; "&TEXT(INDEX(Terna_Proceso!I$27:I$34,MATCH("110",Terna_Proceso!$E$27:$E$34,0)),"#,##0")&"; "&TEXT(INDEX(Terna_Proceso!J$27:J$34,MATCH("110",Terna_Proceso!$E$27:$E$34,0)),"#,##0")&")" -> (6,200; 6,131; 2,735) | D15: ="("&TEXT(INDEX(Terna_Proceso!H$27:H$34,MATCH("100",Terna_Proceso!$E$27:$E$34,0)),"#,##0")&"; "&TEXT(INDEX(Terna_Proceso!I$27:I$34,MATCH("100",Terna_Proceso!$E$27:$E$34,0)),"#,##0")&"; "&TEXT(INDEX(Terna_Proceso!J$27:J$34,MATCH("100",Terna_Proceso!$E$27:$E$34,0)),"#,##0")&")" -> (7,960; 4,372; 2,735)
A16: J1: Ana NO OFRECE | B16: ="("&TEXT(INDEX(Terna_Proceso!H$27:H$34,MATCH("010",Terna_Proceso!$E$27:$E$34,0)),"#,##0")&"; "&TEXT(INDEX(Terna_Proceso!I$27:I$34,MATCH("010",Terna_Proceso!$E$27:$E$34,0)),"#,##0")&"; "&TEXT(INDEX(Terna_Proceso!J$27:J$34,MATCH("010",Terna_Proceso!$E$27:$E$34,0)),"#,##0")&")" -> (1,969; 10,363; 2,735) | D16: ="("&TEXT(INDEX(Terna_Proceso!H$27:H$34,MATCH("000",Terna_Proceso!$E$27:$E$34,0)),"#,##0")&"; "&TEXT(INDEX(Terna_Proceso!I$27:I$34,MATCH("000",Terna_Proceso!$E$27:$E$34,0)),"#,##0")&"; "&TEXT(INDEX(Terna_Proceso!J$27:J$34,MATCH("000",Terna_Proceso!$E$27:$E$34,0)),"#,##0")&")" -> (1,969; 4,372; 2,735)
A19: B. Matriz SUMA NULA – u = V − base media (S/)
A21: J3: Martina OFRECE
B22: J2: Berry OFRECE | D22: J2: Berry NO OFRECE
A23: J1: Ana OFRECE | B23: =INDEX(Terna_Proceso!Q$27:Q$34,MATCH("111",Terna_Proceso!$E$27:$E$34,0))&IF(INDEX(Terna_Proceso!X$27:X$34,MATCH("111",Terna_Proceso!$E$27:$E$34,0))="NASH"," ◄ NASH","") -> (-162; 552; -390) ◄ NASH | D23: =INDEX(Terna_Proceso!Q$27:Q$34,MATCH("101",Terna_Proceso!$E$27:$E$34,0))&IF(INDEX(Terna_Proceso!X$27:X$34,MATCH("101",Terna_Proceso!$E$27:$E$34,0))="NASH"," ◄ NASH","") -> (564; -650; 86)
A24: J1: Ana NO OFRECE | B24: =INDEX(Terna_Proceso!Q$27:Q$34,MATCH("011",Terna_Proceso!$E$27:$E$34,0))&IF(INDEX(Terna_Proceso!X$27:X$34,MATCH("011",Terna_Proceso!$E$27:$E$34,0))="NASH"," ◄ NASH","") -> (-3,053; 1,673; 1,380) | D24: =INDEX(Terna_Proceso!Q$27:Q$34,MATCH("001",Terna_Proceso!$E$27:$E$34,0))&IF(INDEX(Terna_Proceso!X$27:X$34,MATCH("001",Terna_Proceso!$E$27:$E$34,0))="NASH"," ◄ NASH","") -> (-3,053; -650; 3,703)
A27: J3: Martina NO OFRECE
B28: J2: Berry OFRECE | D28: J2: Berry NO OFRECE
A29: J1: Ana OFRECE | B29: =INDEX(Terna_Proceso!Q$27:Q$34,MATCH("110",Terna_Proceso!$E$27:$E$34,0))&IF(INDEX(Terna_Proceso!X$27:X$34,MATCH("110",Terna_Proceso!$E$27:$E$34,0))="NASH"," ◄ NASH","") -> (1,178; 1,109; -2,287) | D29: =INDEX(Terna_Proceso!Q$27:Q$34,MATCH("100",Terna_Proceso!$E$27:$E$34,0))&IF(INDEX(Terna_Proceso!X$27:X$34,MATCH("100",Terna_Proceso!$E$27:$E$34,0))="NASH"," ◄ NASH","") -> (2,937; -650; -2,287)
A30: J1: Ana NO OFRECE | B30: =INDEX(Terna_Proceso!Q$27:Q$34,MATCH("010",Terna_Proceso!$E$27:$E$34,0))&IF(INDEX(Terna_Proceso!X$27:X$34,MATCH("010",Terna_Proceso!$E$27:$E$34,0))="NASH"," ◄ NASH","") -> (-3,053; 5,340; -2,287) | D30: =INDEX(Terna_Proceso!Q$27:Q$34,MATCH("000",Terna_Proceso!$E$27:$E$34,0))&IF(INDEX(Terna_Proceso!X$27:X$34,MATCH("000",Terna_Proceso!$E$27:$E$34,0))="NASH"," ◄ NASH","") -> (-1,056; 1,347; -291)
A33: C. Mejores respuestas (por qué la terna de equilibrio es la que es)
A34: Jugador | B34: Los otros dos hacen… | C34: Pago si OFRECE | D34: Pago si NO ofrece | E34: Mejor respuesta | F34: Ventaja de ofrecer (S/)
A35: Ana | B35: Berry ofrece, Martina ofrece | C35: =INDEX(Terna_Proceso!M$27:M$34,MATCH("111",Terna_Proceso!$E$27:$E$34,0)) -> -162.13118 | D35: =INDEX(Terna_Proceso!M$27:M$34,MATCH("011",Terna_Proceso!$E$27:$E$34,0)) -> -3053.1312 | E35: =IF(C35>D35,"OFRECER","NO ofrecer") -> OFRECER | F35: =C35-D35 -> 2891
A36: Ana | B36: Berry ofrece, Martina NO ofrece | C36: =INDEX(Terna_Proceso!M$27:M$34,MATCH("110",Terna_Proceso!$E$27:$E$34,0)) -> 1178.1471 | D36: =INDEX(Terna_Proceso!M$27:M$34,MATCH("010",Terna_Proceso!$E$27:$E$34,0)) -> -3053.1312 | E36: =IF(C36>D36,"OFRECER","NO ofrecer") -> OFRECER | F36: =C36-D36 -> 4231.2783
A37: Ana | B37: Berry NO ofrece, Martina ofrece | C37: =INDEX(Terna_Proceso!M$27:M$34,MATCH("101",Terna_Proceso!$E$27:$E$34,0)) -> 563.52309 | D37: =INDEX(Terna_Proceso!M$27:M$34,MATCH("001",Terna_Proceso!$E$27:$E$34,0)) -> -3053.1312 | E37: =IF(C37>D37,"OFRECER","NO ofrecer") -> OFRECER | F37: =C37-D37 -> 3616.6543
A38: Ana | B38: Berry NO ofrece, Martina NO ofrece | C38: =INDEX(Terna_Proceso!M$27:M$34,MATCH("100",Terna_Proceso!$E$27:$E$34,0)) -> 2937.3043 | D38: =INDEX(Terna_Proceso!M$27:M$34,MATCH("000",Terna_Proceso!$E$27:$E$34,0)) -> -1056.3194 | E38: =IF(C38>D38,"OFRECER","NO ofrecer") -> OFRECER | F38: =C38-D38 -> 3993.6237
A39: Berry | B39: Ana ofrece, Martina ofrece | C39: =INDEX(Terna_Proceso!N$27:N$34,MATCH("111",Terna_Proceso!$E$27:$E$34,0)) -> 551.96237 | D39: =INDEX(Terna_Proceso!N$27:N$34,MATCH("101",Terna_Proceso!$E$27:$E$34,0)) -> -649.97312 | E39: =IF(C39>D39,"OFRECER","NO ofrecer") -> OFRECER | F39: =C39-D39 -> 1201.9355
A40: Berry | B40: Ana ofrece, Martina NO ofrece | C40: =INDEX(Terna_Proceso!N$27:N$34,MATCH("110",Terna_Proceso!$E$27:$E$34,0)) -> 1109.1841 | D40: =INDEX(Terna_Proceso!N$27:N$34,MATCH("100",Terna_Proceso!$E$27:$E$34,0)) -> -649.97312 | E40: =IF(C40>D40,"OFRECER","NO ofrecer") -> OFRECER | F40: =C40-D40 -> 1759.1572
A41: Berry | B41: Ana NO ofrece, Martina ofrece | C41: =INDEX(Terna_Proceso!N$27:N$34,MATCH("011",Terna_Proceso!$E$27:$E$34,0)) -> 1673.0683 | D41: =INDEX(Terna_Proceso!N$27:N$34,MATCH("001",Terna_Proceso!$E$27:$E$34,0)) -> -649.97312 | E41: =IF(C41>D41,"OFRECER","NO ofrecer") -> OFRECER | F41: =C41-D41 -> 2323.0414
A42: Berry | B42: Ana NO ofrece, Martina NO ofrece | C42: =INDEX(Terna_Proceso!N$27:N$34,MATCH("010",Terna_Proceso!$E$27:$E$34,0)) -> 5340.4624 | D42: =INDEX(Terna_Proceso!N$27:N$34,MATCH("000",Terna_Proceso!$E$27:$E$34,0)) -> 1346.8387 | E42: =IF(C42>D42,"OFRECER","NO ofrecer") -> OFRECER | F42: =C42-D42 -> 3993.6237
A43: Martina | B43: Ana ofrece, Berry ofrece | C43: =INDEX(Terna_Proceso!O$27:O$34,MATCH("111",Terna_Proceso!$E$27:$E$34,0)) -> -389.83118 | D43: =INDEX(Terna_Proceso!O$27:O$34,MATCH("110",Terna_Proceso!$E$27:$E$34,0)) -> -2287.3312 | E43: =IF(C43>D43,"OFRECER","NO ofrecer") -> OFRECER | F43: =C43-D43 -> 1897.5
A44: Martina | B44: Ana ofrece, Berry NO ofrece | C44: =INDEX(Terna_Proceso!O$27:O$34,MATCH("101",Terna_Proceso!$E$27:$E$34,0)) -> 86.450029 | D44: =INDEX(Terna_Proceso!O$27:O$34,MATCH("100",Terna_Proceso!$E$27:$E$34,0)) -> -2287.3312 | E44: =IF(C44>D44,"OFRECER","NO ofrecer") -> OFRECER | F44: =C44-D44 -> 2373.7812
A45: Martina | B45: Ana NO ofrece, Berry ofrece | C45: =INDEX(Terna_Proceso!O$27:O$34,MATCH("011",Terna_Proceso!$E$27:$E$34,0)) -> 1380.0629 | D45: =INDEX(Terna_Proceso!O$27:O$34,MATCH("010",Terna_Proceso!$E$27:$E$34,0)) -> -2287.3312 | E45: =IF(C45>D45,"OFRECER","NO ofrecer") -> OFRECER | F45: =C45-D45 -> 3667.3941
A46: Martina | B46: Ana NO ofrece, Berry NO ofrece | C46: =INDEX(Terna_Proceso!O$27:O$34,MATCH("001",Terna_Proceso!$E$27:$E$34,0)) -> 3703.1043 | D46: =INDEX(Terna_Proceso!O$27:O$34,MATCH("000",Terna_Proceso!$E$27:$E$34,0)) -> -290.51935 | E46: =IF(C46>D46,"OFRECER","NO ofrecer") -> OFRECER | F46: =C46-D46 -> 3993.6237
A47: ¿Ofrecer es estrategia dominante para los tres? | E47: =IF(COUNTIF(E35:E46,"OFRECER")=COUNTA(E35:E46),"SÍ","NO") -> SÍ
A50: D. Interpretación de 3 ternas (texto con cifras vinculadas)
A51: Terna 1 – Todos ofrecen (equilibrio)
A52: ="Terna suma nula "&INDEX(Terna_Proceso!Q$27:Q$34,MATCH("111",Terna_Proceso!$E$27:$E$34,0))&" → Ana "&IF(INDEX(Terna_Proceso!M$27:M$34,MATCH("111",Terna_Proceso!$E$27:$E$34,0))>=0,"queda ","queda ")&TEXT(ABS(INDEX(Terna_Proceso!M$27:M$34,MATCH("111",Terna_Proceso!$E$27:$E$34,0))),"#,##0")&IF(INDEX(Terna_Proceso!M$27:M$34,MATCH("111",Terna_Proceso!$E$27:$E$34,0))>=0," por encima"," por debajo")&" de la media; Berry "&TEXT(ABS(INDEX(Terna_Proceso!N$27:N$34,MATCH("111",Terna_Proceso!$E$27:$E$34,0))),"#,##0")&IF(INDEX(Terna_Proceso!N$27:N$34,MATCH("111",Terna_Proceso!$E$27:$E$34,0))>=0," por encima"," por debajo")&"; Martina "&TEXT(ABS(INDEX(Terna_Proceso!O$27:O$34,MATCH("111",Terna_Proceso!$E$27:$E$34,0))),"#,##0")&IF(INDEX(Terna_Proceso!O$27:O$34,MATCH("111",Terna_Proceso!$E$27:$E$34,0))>=0," por encima."," por debajo.") -> Terna suma nula (-162; 552; -390) → Ana queda 162 por debajo de la media; Berry 552 por encima; Martina 390 por debajo.
A53: Cada empresa conserva su propia venta de k; nadie transfiere ventas. Las diferencias vienen sólo del tamaño de cada negocio respecto a la media del mercado.
A55: Terna 2 – Ana sale de k
A56: ="Terna suma nula "&INDEX(Terna_Proceso!Q$27:Q$34,MATCH("011",Terna_Proceso!$E$27:$E$34,0))&" → Ana "&IF(INDEX(Terna_Proceso!M$27:M$34,MATCH("011",Terna_Proceso!$E$27:$E$34,0))>=0,"queda ","queda ")&TEXT(ABS(INDEX(Terna_Proceso!M$27:M$34,MATCH("011",Terna_Proceso!$E$27:$E$34,0))),"#,##0")&IF(INDEX(Terna_Proceso!M$27:M$34,MATCH("011",Terna_Proceso!$E$27:$E$34,0))>=0," por encima"," por debajo")&" de la media; Berry "&TEXT(ABS(INDEX(Terna_Proceso!N$27:N$34,MATCH("011",Terna_Proceso!$E$27:$E$34,0))),"#,##0")&IF(INDEX(Terna_Proceso!N$27:N$34,MATCH("011",Terna_Proceso!$E$27:$E$34,0))>=0," por encima"," por debajo")&"; Martina "&TEXT(ABS(INDEX(Terna_Proceso!O$27:O$34,MATCH("011",Terna_Proceso!$E$27:$E$34,0))),"#,##0")&IF(INDEX(Terna_Proceso!O$27:O$34,MATCH("011",Terna_Proceso!$E$27:$E$34,0))>=0," por encima."," por debajo.") -> Terna suma nula (-3,053; 1,673; 1,380) → Ana queda 3,053 por debajo de la media; Berry 1,673 por encima; Martina 1,380 por encima.
A57: Ana pierde su venta de k y la transfieren Berry y Martina según su cuota: salir es castigado y beneficia a los rivales.
A59: Terna 3 – Nadie ofrece k
A60: ="Terna suma nula "&INDEX(Terna_Proceso!Q$27:Q$34,MATCH("000",Terna_Proceso!$E$27:$E$34,0))&" → Ana "&IF(INDEX(Terna_Proceso!M$27:M$34,MATCH("000",Terna_Proceso!$E$27:$E$34,0))>=0,"queda ","queda ")&TEXT(ABS(INDEX(Terna_Proceso!M$27:M$34,MATCH("000",Terna_Proceso!$E$27:$E$34,0))),"#,##0")&IF(INDEX(Terna_Proceso!M$27:M$34,MATCH("000",Terna_Proceso!$E$27:$E$34,0))>=0," por encima"," por debajo")&" de la media; Berry "&TEXT(ABS(INDEX(Terna_Proceso!N$27:N$34,MATCH("000",Terna_Proceso!$E$27:$E$34,0))),"#,##0")&IF(INDEX(Terna_Proceso!N$27:N$34,MATCH("000",Terna_Proceso!$E$27:$E$34,0))>=0," por encima"," por debajo")&"; Martina "&TEXT(ABS(INDEX(Terna_Proceso!O$27:O$34,MATCH("000",Terna_Proceso!$E$27:$E$34,0))),"#,##0")&IF(INDEX(Terna_Proceso!O$27:O$34,MATCH("000",Terna_Proceso!$E$27:$E$34,0))>=0," por encima."," por debajo.") -> Terna suma nula (-1,056; 1,347; -291) → Ana queda 1,056 por debajo de la media; Berry 1,347 por encima; Martina 291 por debajo.
A61: El mercado de k desaparece y cada empresa se queda sólo con el resto de productos; es una terna posible pero inestable: cualquiera que vuelva a ofrecer k captura todo el mercado de k.

Sheet Datos_Comp
A1: Datos cuantitativos – Competencia entre empresas (cantidades)
A2: Ana (J1) vs. Berry Blue (J2) en el producto en disputa. Cada fila empareja el día N° de cada negocio (30 días).
A4: Producto en disputa | B4: =Datos_3J!B5 -> Cerveza | E4: Cantidades q: unidades vendidas por día (hojas Ventas_*). Precios p: precio de venta registrado cada día (S/, entrada en azul; varía por promociones de fin de semana y cambios de lista). Utilidad diaria observada = (p − c)·q.
A5: Costo unitario Ana c1 (S/) | B5: =INDEX(Datos_3J!B20:B26,Datos_3J!B6) -> 5.5
A6: Costo unitario Berry c2 (S/) | B6: =INDEX(Datos_3J!C20:C26,Datos_3J!B6) -> 6.3
A7: Precio de lista Ana / Berry (S/) | B7: =INDEX(Datos_3J!B10:B16,Datos_3J!B6) -> 7 | C7: =INDEX(Datos_3J!C10:C16,Datos_3J!B6) -> 9
A9: Serie diaria
A10: N° día | B10: Fecha Ana | C10: Fecha Berry | D10: q1 Ana (unid/día) | E10: q2 Berry (unid/día) | F10: p1 Ana (S/) | G10: p2 Berry (S/) | H10: u1 observada (S/) | I10: u2 observada (S/) | J10: p̂1 ajustado | K10: p̂2 ajustado
A11: 1 | B11: =Ventas_Ana!B14 -> 45836 | C11: =Ventas_Berry!B14 -> 46235 | D11: =INDEX(Ventas_Ana!D14:J14,Datos_3J!$B$6) -> 16 | E11: =INDEX(Ventas_Berry!D14:J14,Datos_3J!$B$6) -> 4 | F11: 6.5 | G11: 9.5 | H11: =(F11-$B$5)*D11 -> 16 | I11: =(G11-$B$6)*E11 -> 12.8 | J11: =Regresión!$E$38+Regresión!$E$39*D11+Regresión!$E$40*E11 -> 6.9289191 | K11: =Regresión!$L$38+Regresión!$L$39*E11+Regresión!$L$40*D11 -> 9.0379553
A12: 2 | B12: =Ventas_Ana!B15 -> 45837 | C12: =Ventas_Berry!B15 -> 46236 | D12: =INDEX(Ventas_Ana!D15:J15,Datos_3J!$B$6) -> 20 | E12: =INDEX(Ventas_Berry!D15:J15,Datos_3J!$B$6) -> 1 | F12: 7 | G12: 9.5 | H12: =(F12-$B$5)*D12 -> 30 | I12: =(G12-$B$6)*E12 -> 3.2 | J12: =Regresión!$E$38+Regresión!$E$39*D12+Regresión!$E$40*E12 -> 6.8447009 | K12: =Regresión!$L$38+Regresión!$L$39*E12+Regresión!$L$40*D12 -> 9.5172004
A13: 3 | B13: =Ventas_Ana!B16 -> 45838 | C13: =Ventas_Berry!B16 -> 46237 | D13: =INDEX(Ventas_Ana!D16:J16,Datos_3J!$B$6) -> 7 | E13: =INDEX(Ventas_Berry!D16:J16,Datos_3J!$B$6) -> 5 | F13: 7.5 | G13: 10 | H13: =(F13-$B$5)*D13 -> 14 | I13: =(G13-$B$6)*E13 -> 18.5 | J13: =Regresión!$E$38+Regresión!$E$39*D13+Regresión!$E$40*E13 -> 7.5072347 | K13: =Regresión!$L$38+Regresión!$L$39*E13+Regresión!$L$40*D13 -> 9.4437535
A14: 4 | B14: =Ventas_Ana!B17 -> 45839 | C14: =Ventas_Berry!B17 -> 46238 | D14: =INDEX(Ventas_Ana!D17:J17,Datos_3J!$B$6) -> 9 | E14: =INDEX(Ventas_Berry!D17:J17,Datos_3J!$B$6) -> 5 | F14: 7.5 | G14: 9 | H14: =(F14-$B$5)*D14 -> 18 | I14: =(G14-$B$6)*E14 -> 13.5 | J14: =Regresión!$E$38+Regresión!$E$39*D14+Regresión!$E$40*E14 -> 7.3636931 | K14: =Regresión!$L$38+Regresión!$L$39*E14+Regresión!$L$40*D14 -> 9.2962196
A15: 5 | B15: =Ventas_Ana!B18 -> 45840 | C15: =Ventas_Berry!B18 -> 46239 | D15: =INDEX(Ventas_Ana!D18:J18,Datos_3J!$B$6) -> 6 | E15: =INDEX(Ventas_Berry!D18:J18,Datos_3J!$B$6) -> 5 | F15: 7.5 | G15: 8.5 | H15: =(F15-$B$5)*D15 -> 12 | I15: =(G15-$B$6)*E15 -> 11 | J15: =Regresión!$E$38+Regresión!$E$39*D15+Regresión!$E$40*E15 -> 7.5790055 | K15: =Regresión!$L$38+Regresión!$L$39*E15+Regresión!$L$40*D15 -> 9.5175204
A16: 6 | B16: =Ventas_Ana!B19 -> 45841 | C16: =Ventas_Berry!B19 -> 46240 | D16: =INDEX(Ventas_Ana!D19:J19,Datos_3J!$B$6) -> 11 | E16: =INDEX(Ventas_Berry!D19:J19,Datos_3J!$B$6) -> 6 | F16: 7.5 | G16: 9 | H16: =(F16-$B$5)*D16 -> 22 | I16: =(G16-$B$6)*E16 -> 16.2 | J16: =Regresión!$E$38+Regresión!$E$39*D16+Regresión!$E$40*E16 -> 7.1525298 | K16: =Regresión!$L$38+Regresión!$L$39*E16+Regresión!$L$40*D16 -> 8.8905813
A17: 7 | B17: =Ventas_Ana!B20 -> 45842 | C17: =Ventas_Berry!B20 -> 46241 | D17: =INDEX(Ventas_Ana!D20:J20,Datos_3J!$B$6) -> 10 | E17: =INDEX(Ventas_Berry!D20:J20,Datos_3J!$B$6) -> 5 | F17: 7.5 | G17: 9.5 | H17: =(F17-$B$5)*D17 -> 20 | I17: =(G17-$B$6)*E17 -> 16 | J17: =Regresión!$E$38+Regresión!$E$39*D17+Regresión!$E$40*E17 -> 7.2919223 | K17: =Regresión!$L$38+Regresión!$L$39*E17+Regresión!$L$40*D17 -> 9.2224526
A18: 8 | B18: =Ventas_Ana!B21 -> 45843 | C18: =Ventas_Berry!B21 -> 46242 | D18: =INDEX(Ventas_Ana!D21:J21,Datos_3J!$B$6) -> 14 | E18: =INDEX(Ventas_Berry!D21:J21,Datos_3J!$B$6) -> 1 | F18: 7.5 | G18: 10 | H18: =(F18-$B$5)*D18 -> 28 | I18: =(G18-$B$6)*E18 -> 3.7 | J18: =Regresión!$E$38+Regresión!$E$39*D18+Regresión!$E$40*E18 -> 7.2753258 | K18: =Regresión!$L$38+Regresión!$L$39*E18+Regresión!$L$40*D18 -> 9.9598022
A19: 9 | B19: =Ventas_Ana!B22 -> 45844 | C19: =Ventas_Berry!B22 -> 46243 | D19: =INDEX(Ventas_Ana!D22:J22,Datos_3J!$B$6) -> 26 | E19: =INDEX(Ventas_Berry!D22:J22,Datos_3J!$B$6) -> 7 | F19: 6 | G19: 7.5 | H19: =(F19-$B$5)*D19 -> 13 | I19: =(G19-$B$6)*E19 -> 8.4 | J19: =Regresión!$E$38+Regresión!$E$39*D19+Regresión!$E$40*E19 -> 6.0083459 | K19: =Regresión!$L$38+Regresión!$L$39*E19+Regresión!$L$40*D19 -> 7.5259727
A20: 10 | B20: =Ventas_Ana!B23 -> 45845 | C20: =Ventas_Berry!B23 -> 46244 | D20: =INDEX(Ventas_Ana!D23:J23,Datos_3J!$B$6) -> 12 | E20: =INDEX(Ventas_Berry!D23:J23,Datos_3J!$B$6) -> 8 | F20: 7 | G20: 8 | H20: =(F20-$B$5)*D20 -> 18 | I20: =(G20-$B$6)*E20 -> 13.6 | J20: =Regresión!$E$38+Regresión!$E$39*D20+Regresión!$E$40*E20 -> 6.9455156 | K20: =Regresión!$L$38+Regresión!$L$39*E20+Regresión!$L$40*D20 -> 8.3006057
A21: 11 | B21: =Ventas_Ana!B24 -> 45846 | C21: =Ventas_Berry!B24 -> 46245 | D21: =INDEX(Ventas_Ana!D24:J24,Datos_3J!$B$6) -> 6 | E21: =INDEX(Ventas_Berry!D24:J24,Datos_3J!$B$6) -> 4 | F21: 7.5 | G21: 10 | H21: =(F21-$B$5)*D21 -> 12 | I21: =(G21-$B$6)*E21 -> 14.8 | J21: =Regresión!$E$38+Regresión!$E$39*D21+Regresión!$E$40*E21 -> 7.6466272 | K21: =Regresión!$L$38+Regresión!$L$39*E21+Regresión!$L$40*D21 -> 9.7756248
A22: 12 | B22: =Ventas_Ana!B25 -> 45847 | C22: =Ventas_Berry!B25 -> 46246 | D22: =INDEX(Ventas_Ana!D25:J25,Datos_3J!$B$6) -> 8 | E22: =INDEX(Ventas_Berry!D25:J25,Datos_3J!$B$6) -> 2 | F22: 8 | G22: 10.5 | H22: =(F22-$B$5)*D22 -> 20 | I22: =(G22-$B$6)*E22 -> 8.4 | J22: =Regresión!$E$38+Regresión!$E$39*D22+Regresión!$E$40*E22 -> 7.638329 | K22: =Regresión!$L$38+Regresión!$L$39*E22+Regresión!$L$40*D22 -> 10.1443
... A40: 30 | B40: =Ventas_Ana!B43 -> 45865 | C40: =Ventas_Berry!B43 -> 46264 | D40: =INDEX(Ventas_Ana!D43:J43,Datos_3J!$B$6) -> 23 | E40: =INDEX(Ventas_Berry!D43:J43,Datos_3J!$B$6) -> 1 | F40: 6.5 | G40: 9 | H40: =(F40-$B$5)*D40 -> 23 | I40: =(G40-$B$6)*E40 -> 2.7 | J40: =Regresión!$E$38+Regresión!$E$39*D40+Regresión!$E$40*E40 -> 6.6293884 | K40: =Regresión!$L$38+Regresión!$L$39*E40+Regresión!$L$40*D40 -> 9.2958996
A42: Media | D42: =AVERAGE(D11:D40) -> 13.766667 | E42: =AVERAGE(E11:E40) -> 4.3333333 | F42: =AVERAGE(F11:F40) -> 7.0666667 | G42: =AVERAGE(G11:G40) -> 9.1166667 | H42: =AVERAGE(H11:H40) -> 18.283333 | I42: =AVERAGE(I11:I40) -> 10.866667 | J42: =AVERAGE(J11:J40) -> 7.0666667 | K42: =AVERAGE(K11:K40) -> 9.1166667
A43: Desv. estándar | D43: =STDEV(D11:D40) -> 6.8060994 | E43: =STDEV(E11:E40) -> 2.2488822 | F43: =STDEV(F11:F40) -> 0.61213777 | G43: =STDEV(G11:G40) -> 0.89715386 | H43: =STDEV(H11:H40) -> 6.1120053 | I43: =STDEV(I11:I40) -> 4.5628434 | J43: =STDEV(J11:J40) -> 0.52175262 | K43: =STDEV(K11:K40) -> 0.79380747
A44: Mínimo | D44: =MIN(D11:D40) -> 3 | E44: =MIN(E11:E40) -> 1 | F44: =MIN(F11:F40) -> 6 | G44: =MIN(G11:G40) -> 7.5 | H44: =MIN(H11:H40) -> 7.5 | I44: =MIN(I11:I40) -> 2.7 | J44: =MIN(J11:J40) -> 5.7254117 | K44: =MIN(K11:K40) -> 7.0465675
A45: Máximo | D45: =MAX(D11:D40) -> 29 | E45: =MAX(E11:E40) -> 8 | F45: =MAX(F11:F40) -> 8 | G45: =MAX(G11:G40) -> 10.5 | H45: =MAX(H11:H40) -> 31.5 | I45: =MAX(I11:I40) -> 19.2 | J45: =MAX(J11:J40) -> 7.997183 | K45: =MAX(K11:K40) -> 10.513134
A48: Limitación: las dos series provienen de negocios y calendarios distintos; se emparejan por número de día para tener observaciones conjuntas (q1,q2,p1,p2). Con más tiempo, lo ideal es medir ambos negocios en las mismas fechas.

Sheet Regresión
A1: Generación de las funciones de demanda inversa (regresión lineal múltiple)
A2: p_i = α_i + β_i·q_i + γ_i·q_j · Ecuaciones normales resueltas por Gauss-Jordan y verificadas con LINEST.
A4: Sumas necesarias (n = 30 observaciones)
A5: n | B5: =COUNT(Datos_Comp!$D$11:$D$40) -> 30
A6: Σ q1 | B6: =SUM(Datos_Comp!$D$11:$D$40) -> 413
A7: Σ q2 | B7: =SUM(Datos_Comp!$E$11:$E$40) -> 130
A8: Σ q1² | B8: =SUMSQ(Datos_Comp!$D$11:$D$40) -> 7029
A9: Σ q2² | B9: =SUMSQ(Datos_Comp!$E$11:$E$40) -> 710
A10: Σ q1·q2 | B10: =SUMPRODUCT(Datos_Comp!$D$11:$D$40,Datos_Comp!$E$11:$E$40) -> 1821
A11: Σ p1 | B11: =SUM(Datos_Comp!$F$11:$F$40) -> 212
A12: Σ p1·q1 | B12: =SUMPRODUCT(Datos_Comp!$F$11:$F$40,Datos_Comp!$D$11:$D$40) -> 2820
A13: Σ p1·q2 | B13: =SUMPRODUCT(Datos_Comp!$F$11:$F$40,Datos_Comp!$E$11:$E$40) -> 906.5
A14: Σ p2 | B14: =SUM(Datos_Comp!$G$11:$G$40) -> 273.5
A15: Σ p2·q1 | B15: =SUMPRODUCT(Datos_Comp!$G$11:$G$40,Datos_Comp!$D$11:$D$40) -> 3658
A16: Σ p2·q2 | B16: =SUMPRODUCT(Datos_Comp!$G$11:$G$40,Datos_Comp!$E$11:$E$40) -> 1145
A19: Regresión 1 – Ana: p1 = α1 + β1·q1 + γ1·q2 | H19: Regresión 2 – Berry: p2 = α2 + β2·q2 + γ2·q1
A22: Matriz aumentada [X'X | X'y] | B22: α | C22: β (q propia) | D22: γ (q rival) | E22: término indep. (b) | H22: Matriz aumentada [X'X | X'y] | I22: α | J22: β (q propia) | K22: γ (q rival) | L22: término indep. (b)
A23: F1 | B23: =$B$5 -> 30 | C23: =$B$6 -> 413 | D23: =$B$7 -> 130 | E23: =$B$11 -> 212 | H23: F1 | I23: =$B$5 -> 30 | J23: =$B$7 -> 130 | K23: =$B$6 -> 413 | L23: =$B$14 -> 273.5
A24: F2 | B24: =$B$6 -> 413 | C24: =$B$8 -> 7029 | D24: =$B$10 -> 1821 | E24: =$B$12 -> 2820 | H24: F2 | I24: =$B$7 -> 130 | J24: =$B$9 -> 710 | K24: =$B$10 -> 1821 | L24: =$B$16 -> 1145
A25: F3 | B25: =$B$7 -> 130 | C25: =$B$10 -> 1821 | D25: =$B$9 -> 710 | E25: =$B$13 -> 906.5 | H25: F3 | I25: =$B$6 -> 413 | J25: =$B$10 -> 1821 | K25: =$B$8 -> 7029 | L25: =$B$15 -> 3658
A27: Paso 1: pivote en F1 (F1 ÷ pivote; F2,F3 − factor·F1) | B27: α | C27: β (q propia) | D27: γ (q rival) | E27: término indep. (b) | H27: Paso 1: pivote en F1 (F1 ÷ pivote; F2,F3 − factor·F1) | I27: α | J27: β (q propia) | K27: γ (q rival) | L27: término indep. (b)
A28: F1 | B28: =B23/B23 -> 1 | C28: =C23/B23 -> 13.766667 | D28: =D23/B23 -> 4.3333333 | E28: =E23/B23 -> 7.0666667 | H28: F1 | I28: =I23/I23 -> 1 | J28: =J23/I23 -> 4.3333333 | K28: =K23/I23 -> 13.766667 | L28: =L23/I23 -> 9.1166667
A29: F2 | B29: =B24-B24*B28 -> 0 | C29: =C24-B24*C28 -> 1343.3667 | D29: =D24-B24*D28 -> 31.333333 | E29: =E24-B24*E28 -> -98.533333 | H29: F2 | I29: =I24-I24*I28 -> 0 | J29: =J24-I24*J28 -> 146.66667 | K29: =K24-I24*K28 -> 31.333333 | L29: =L24-I24*L28 -> -40.166667
A30: F3 | B30: =B25-B25*B28 -> 0 | C30: =C25-B25*C28 -> 31.333333 | D30: =D25-B25*D28 -> 146.66667 | E30: =E25-B25*E28 -> -12.166667 | H30: F3 | I30: =I25-I25*I28 -> 0 | J30: =J25-I25*J28 -> 31.333333 | K30: =K25-I25*K28 -> 1343.3667 | L30: =L25-I25*L28 -> -107.18333
A32: Paso 2: pivote en F2 | B32: α | C32: β (q propia) | D32: γ (q rival) | E32: término indep. (b) | H32: Paso 2: pivote en F2 | I32: α | J32: β (q propia) | K32: γ (q rival) | L32: término indep. (b)
A33: F1 | B33: =B28-C28*B34 -> 1 | C33: =C28-C28*C34 -> 0 | D33: =D28-C28*D34 -> 4.0122329 | E33: =E28-C28*E34 -> 8.0764249 | H33: F1 | I33: =I28-J28*I34 -> 1 | J33: =J28-J28*J34 -> 0 | K33: =K28-J28*K34 -> 12.840909 | L33: =L28-J28*L34 -> 10.303409
A34: F2 | B34: =B29/C29 -> 0 | C34: =C29/C29 -> 1 | D34: =D29/C29 -> 0.023324483 | E34: =E29/C29 -> -0.073348056 | H34: F2 | I34: =I29/J29 -> 0 | J34: =J29/J29 -> 1 | K34: =K29/J29 -> 0.21363636 | L34: =L29/J29 -> -0.27386364
A35: F3 | B35: =B30-C30*B34 -> 0 | C35: =C30-C30*C34 -> 0 | D35: =D30-C30*D34 -> 145.93583 | E35: =E30-C30*E34 -> -9.8684276 | H35: F3 | I35: =I30-J30*I34 -> 0 | J35: =J30-J30*J34 -> 0 | K35: =K30-J30*K34 -> 1336.6727 | L35: =L30-J30*L34 -> -98.602273
A37: Paso 3: pivote en F3 → columna derecha = solución | B37: α | C37: β (q propia) | D37: γ (q rival) | E37: término indep. (b) | H37: Paso 3: pivote en F3 → columna derecha = solución | I37: α | J37: β (q propia) | K37: γ (q rival) | L37: término indep. (b)
A38: F1 | B38: =B33-D33*B40 -> 1 | C38: =C33-D33*C40 -> 0 | D38: =D33-D33*D40 -> 0 | E38: =E33-D33*E40 -> 8.3477389 | H38: F1 | I38: =I33-K33*I40 -> 1 | J38: =J33-K33*J40 -> 0 | K38: =K33-K33*K40 -> 0 | L38: =L33-K33*L40 -> 11.250644
A39: F2 | B39: =B34-D34*B40 -> 0 | C39: =C34-D34*C40 -> 1 | D39: =D34-D34*D40 -> 0 | E39: =E34-D34*E40 -> -0.071770815 | H39: F2 | I39: =I34-K34*I40 -> 0 | J39: =J34-K34*J40 -> 1 | K39: =K34-K34*K40 -> 0 | L39: =L34-K34*L40 -> -0.25810433
A40: F3 | B40: =B35/D35 -> 0 | C40: =C35/D35 -> 0 | D40: =D35/D35 -> 1 | E40: =E35/D35 -> -0.06762169 | H40: F3 | I40: =I35/K35 -> 0 | J40: =J35/K35 -> 0 | K40: =K35/K35 -> 1 | L40: =L35/K35 -> -0.073766952
A42: Resultados Regresión 1 – Ana
A43: Parámetro | B43: Gauss-Jordan | C43: LINEST (control) | D43: Diferencia | E43: Error estándar | F43: Estadístico t | G43: Lectura económica
A44: α (intercepto) | B44: =E38 -> 8.3477389 | C44: =INDEX(LINEST(Datos_Comp!$F$11:$F$40,Datos_Comp!$D$11:$E$40,TRUE(),TRUE()),1,3) -> 8.3477389 | D44: =B44-C44 -> 0 | E44: =INDEX(LINEST(Datos_Comp!$F$11:$F$40,Datos_Comp!$D$11:$E$40,TRUE(),TRUE()),2,3) -> 0.17703585 | F44: =B44/E44 -> 47.152816 | G44: Precio al que se vendería con q=0 (techo de la demanda)
A45: β (efecto de la q propia) | B45: =E39 -> -0.071770815 | C45: =INDEX(LINEST(Datos_Comp!$F$11:$F$40,Datos_Comp!$D$11:$E$40,TRUE(),TRUE()),1,2) -> -0.071770815 | D45: =B45-C45 -> 0 | E45: =INDEX(LINEST(Datos_Comp!$F$11:$F$40,Datos_Comp!$D$11:$E$40,TRUE(),TRUE()),2,2) -> 0.0090748328 | F45: =B45/E45 -> -7.9087754 | G45: Pendiente propia: vender más obliga a bajar el precio
A46: γ (efecto de la q del rival) | B46: =E40 -> -0.06762169 | C46: =INDEX(LINEST(Datos_Comp!$F$11:$F$40,Datos_Comp!$D$11:$E$40,TRUE(),TRUE()),1,1) -> -0.06762169 | D46: =B46-C46 -> 2.6367797e-16 | E46: =INDEX(LINEST(Datos_Comp!$F$11:$F$40,Datos_Comp!$D$11:$E$40,TRUE(),TRUE()),2,1) -> 0.027464406 | F46: =B46/E46 -> -2.4621574 | G46: Rival vende más → mi precio cae (bienes sustitutos)
A47: R² | B47: =1-SUMXMY2(Datos_Comp!$F$11:$F$40,Datos_Comp!$J$11:$J$40)/DEVSQ(Datos_Comp!$F$11:$F$40) -> 0.72649216 | C47: =INDEX(LINEST(Datos_Comp!$F$11:$F$40,Datos_Comp!$D$11:$E$40,TRUE(),TRUE()),3,1) -> 0.72649216 | D47: =B47-C47 -> 0 | G47: Proporción de la variación del precio explicada por q1 y q2
A48: Error estándar de la regresión (S/) | B48: =SQRT(SUMXMY2(Datos_Comp!$F$11:$F$40,Datos_Comp!$J$11:$J$40)/(COUNT(Datos_Comp!$F$11:$F$40)-3)) -> 0.33178074 | C48: =INDEX(LINEST(Datos_Comp!$F$11:$F$40,Datos_Comp!$D$11:$E$40,TRUE(),TRUE()),3,2) -> 0.33178074 | D48: =B48-C48 -> 0
A49: Signos esperados (β<0 y γ<0) | B49: =IF(AND(B45<0,B46<0),"CUMPLE","REVISAR") -> CUMPLE
A52: Resultados Regresión 2 – Berry
A53: Parámetro | B53: Gauss-Jordan | C53: LINEST (control) | D53: Diferencia | E53: Error estándar | F53: Estadístico t | G53: Lectura económica
A54: α (intercepto) | B54: =L38 -> 11.250644 | C54: =INDEX(LINEST(Datos_Comp!$G$11:$G$40,Datos_Comp!$D$11:$E$40,TRUE(),TRUE()),1,3) -> 11.250644 | D54: =B54-C54 -> 0 | E54: =INDEX(LINEST(Datos_Comp!$G$11:$G$40,Datos_Comp!$D$11:$E$40,TRUE(),TRUE()),2,3) -> 0.23117543 | F54: =B54/E54 -> 48.667126 | G54: Precio al que se vendería con q=0 (techo de la demanda)
A55: β (efecto de la q propia) | B55: =L39 -> -0.25810433 | C55: =INDEX(LINEST(Datos_Comp!$G$11:$G$40,Datos_Comp!$D$11:$E$40,TRUE(),TRUE()),1,1) -> -0.25810433 | D55: =B55-C55 -> -4.4408921e-16 | E55: =INDEX(LINEST(Datos_Comp!$G$11:$G$40,Datos_Comp!$D$11:$E$40,TRUE(),TRUE()),2,1) -> 0.035863334 | F55: =B55/E55 -> -7.1968862 | G55: Pendiente propia: vender más obliga a bajar el precio
A56: γ (efecto de la q del rival) | B56: =L40 -> -0.073766952 | C56: =INDEX(LINEST(Datos_Comp!$G$11:$G$40,Datos_Comp!$D$11:$E$40,TRUE(),TRUE()),1,2) -> -0.073766952 | D56: =B56-C56 -> 0 | E56: =INDEX(LINEST(Datos_Comp!$G$11:$G$40,Datos_Comp!$D$11:$E$40,TRUE(),TRUE()),2,2) -> 0.01185002 | F56: =B56/E56 -> -6.2250487 | G56: Rival vende más → mi precio cae (bienes sustitutos)
A57: R² | B57: =1-SUMXMY2(Datos_Comp!$G$11:$G$40,Datos_Comp!$K$11:$K$40)/DEVSQ(Datos_Comp!$G$11:$G$40) -> 0.78288233 | C57: =INDEX(LINEST(Datos_Comp!$G$11:$G$40,Datos_Comp!$D$11:$E$40,TRUE(),TRUE()),3,1) -> 0.78288233 | D57: =B57-C57 -> 0 | G57: Proporción de la variación del precio explicada por q1 y q2
A58: Error estándar de la regresión (S/) | B58: =SQRT(SUMXMY2(Datos_Comp!$G$11:$G$40,Datos_Comp!$K$11:$K$40)/(COUNT(Datos_Comp!$G$11:$G$40)-3)) -> 0.43324307 | C58: =INDEX(LINEST(Datos_Comp!$G$11:$G$40,Datos_Comp!$D$11:$E$40,TRUE(),TRUE()),3,2) -> 0.43324307 | D58: =B58-C58 -> 0
A59: Signos esperados (β<0 y γ<0) | B59: =IF(AND(B55<0,B56<0),"CUMPLE","REVISAR") -> CUMPLE

Sheet Nash
A1: Solución no cooperativa (Cournot en cantidades)
A2: Cada empresa elige su cantidad maximizando su propia utilidad, tomando como dada la del rival. Equilibrio de Nash = intersección de las curvas de reacción.
A4: 1. Parámetros (vinculados a Regresión y Datos_Comp)
A5: Ana (J1) | B5: Valor | C5: Berry (J2) | D5: Valor
A6: α1 | B6: =Regresión!B44 -> 8.3477389 | C6: α2 | D6: =Regresión!B54 -> 11.250644
A7: β1 (q propia) | B7: =Regresión!B45 -> -0.071770815 | C7: β2 (q propia) | D7: =Regresión!B55 -> -0.25810433
A8: γ1 (q del rival) | B8: =Regresión!B46 -> -0.06762169 | C8: γ2 (q del rival) | D8: =Regresión!B56 -> -0.073766952
A9: c1 (costo unitario) | B9: =Datos_Comp!B5 -> 5.5 | C9: c2 (costo unitario) | D9: =Datos_Comp!B6 -> 6.3
A10: a1 = α1 − c1 | B10: =B6-B9 -> 2.8477389 | C10: a2 = α2 − c2 | D10: =D6-D9 -> 4.9506438
A12: 2. Funciones de utilidad y condiciones de primer orden
A13: u1 = (p1 − c1)·q1 = a1·q1 + β1·q1² + γ1·q1·q2 | C13: u2 = (p2 − c2)·q2 = a2·q2 + β2·q2² + γ2·q1·q2
A14: ∂u1/∂q1 = a1 + 2β1·q1 + γ1·q2 = 0 | C14: ∂u2/∂q2 = a2 + 2β2·q2 + γ2·q1 = 0
A15: Curva de reacción: R1(q2) = −(a1 + γ1·q2)/(2β1) | C15: Curva de reacción: R2(q1) = −(a2 + γ2·q1)/(2β2)
A17: Curva | B17: Intercepto r0 | C17: Pendiente r1 | D17: R(q) = r0 + r1·q_rival
A18: R1 (Ana) | B18: =-B10/(2*B7) -> 19.839115 | C18: =-B8/(2*B7) -> -0.47109462 | D18: ="q1 = "&TEXT(B18,"0.00")&" "&TEXT(C18,"+0.000;-0.000")&"·q2" -> q1 = 19.84 -0.471·q2
A19: R2 (Berry) | B19: =-D10/(2*D7) -> 9.5903927 | C19: =-D8/(2*D7) -> -0.14290142 | D19: ="q2 = "&TEXT(B19,"0.00")&" "&TEXT(C19,"+0.000;-0.000")&"·q1" -> q2 = 9.59 -0.143·q1
A21: 3. Equilibrio de Nash (cantidades por día)
A22: Resultado | B22: Curvas de reacción | C22: Control: Cramer | D22: Diferencia
A23: q1* Ana (unid/día) | B23: =(B18+C18*B19)/(1-C18*C19) -> 16.427 | C23: =(-B10*2*D7+B8*D10)/(4*B7*D7-B8*D8) -> 16.427 | D23: =B23-C23 -> 0
A24: q2* Berry (unid/día) | B24: =B19+C19*B23 -> 7.2429511 | C24: =(-2*B7*D10+D8*B10)/(4*B7*D7-B8*D8) -> 7.2429511 | D24: =B24-C24 -> 0
A25: p1* Ana (S/) | B25: =B6+B7*B23+B8*B24 -> 6.6789791
A26: p2* Berry (S/) | B26: =D6+D7*B24+D8*B23 -> 8.1694371
A27: u1* Ana (S/ por día) | B27: =(B25-B9)*B23 -> 19.36709
A28: u2* Berry (S/ por día) | B28: =(B26-D9)*B24 -> 13.540241
A29: u1* + u2* (S/ por día) | B29: =B27+B28 -> 32.907331
A30: Residuo FOC Ana (debe ser 0) | B30: =B10+2*B7*B23+B8*B24 -> -4.9960036e-16
A31: Residuo FOC Berry (debe ser 0) | B31: =D10+2*D7*B24+D8*B23 -> 0
A33: 4. Condiciones de segundo orden y estabilidad
A34: ∂²u1/∂q1² = 2β1 (<0 → máximo) | B34: =2*B7 -> -0.14354163 | C34: =IF(B34<0,"CUMPLE","REVISAR") -> CUMPLE
A35: ∂²u2/∂q2² = 2β2 (<0 → máximo) | B35: =2*D7 -> -0.51620867 | C35: =IF(B35<0,"CUMPLE","REVISAR") -> CUMPLE
A36: |r1(R1)·r1(R2)| (<1 → estable) | B36: =ABS(C18*C19) -> 0.067320091 | C36: =IF(B36<1,"CUMPLE","REVISAR") -> CUMPLE
A37: 4β1β2 − γ1γ2 (>0 → solución única) | B37: =4*B7*D7-B8*D8 -> 0.069109187 | C37: =IF(B37>0,"CUMPLE","REVISAR") -> CUMPLE
A39: 5. Cómo llegan a Nash: mejores respuestas sucesivas (partiendo de las medias observadas)
A40: Ronda | B40: q1 | C40: q2 | D40: |Δq1| | E40: |Δq2|
A41: 0 | B41: =Datos_Comp!$D$42 -> 13.766667 | C41: =Datos_Comp!$E$42 -> 4.3333333
A42: 1 | B42: =$B$18+$C$18*C41 -> 17.797705 | C42: =$B$19+$C$19*B41 -> 7.6231165 | D42: =ABS(B42-B41) -> 4.0310381 | E42: =ABS(C42-C41) -> 3.2897831
A43: 2 | B43: =$B$18+$C$18*C42 -> 16.247906 | C43: =$B$19+$C$19*B42 -> 7.0470754 | D43: =ABS(B43-B42) -> 1.5497991 | E43: =ABS(C43-C42) -> 0.57604107
A44: 3 | B44: =$B$18+$C$18*C43 -> 16.519276 | C44: =$B$19+$C$19*B43 -> 7.2685439 | D44: =ABS(B44-B43) -> 0.27136985 | E44: =ABS(C44-C43) -> 0.2214685
A45: 4 | B45: =$B$18+$C$18*C44 -> 16.414943 | C45: =$B$19+$C$19*B44 -> 7.2297647 | D45: =ABS(B45-B44) -> 0.10433262 | E45: =ABS(C45-C44) -> 0.038779137
A46: 5 | B46: =$B$18+$C$18*C45 -> 16.433212 | C46: =$B$19+$C$19*B45 -> 7.244674 | D46: =ABS(B46-B45) -> 0.018268643 | E46: =ABS(C46-C45) -> 0.014909279
A47: 6 | B47: =$B$18+$C$18*C46 -> 16.426188 | C47: =$B$19+$C$19*B46 -> 7.2420634 | D47: =ABS(B47-B46) -> 0.0070236813 | E47: =ABS(C47-C46) -> 0.002610615
A48: 7 | B48: =$B$18+$C$18*C47 -> 16.427418 | C48: =$B$19+$C$19*B47 -> 7.2430671 | D48: =ABS(B48-B47) -> 0.0012298467 | E48: =ABS(C48-C47) -> 0.001003694
A49: 8 | B49: =$B$18+$C$18*C48 -> 16.426945 | C49: =$B$19+$C$19*B48 -> 7.2428914 | D49: =ABS(B49-B48) -> 0.00047283486 | E49: =ABS(C49-C48) -> 0.00017574684
A50: 9 | B50: =$B$18+$C$18*C49 -> 16.427028 | C50: =$B$19+$C$19*B49 -> 7.2429589 | D50: =ABS(B50-B49) -> 8.2793391e-05 | E50: =ABS(C50-C49) -> 6.7568773e-05
A51: 10 | B51: =$B$18+$C$18*C50 -> 16.426996 | C51: =$B$19+$C$19*B50 -> 7.2429471 | D51: =ABS(B51-B50) -> 3.1831286e-05 | E51: =ABS(C51-C50) -> 1.1831293e-05
A54: 6. Datos del gráfico de curvas de reacción
A55: q2 (malla) | B55: q1 = R1(q2) | C55: q1 (malla) | D55: q2 = R2(q1) | G55: Puntos | H55: q1 | I55: q2
A56: 0 | B56: =$B$18+$C$18*A56 -> 19.839115 | C56: 0 | D56: =$B$19+$C$19*C56 -> 9.5903927 | G56: Nash | H56: =B23 -> 16.427 | I56: =B24 -> 7.2429511
A57: 1 | B57: =$B$18+$C$18*A57 -> 19.36802 | C57: 2 | D57: =$B$19+$C$19*C57 -> 9.3045898 | G57: Cooperativo | H57: =Cooperativa!B20 -> 14.232302 | I57: =Cooperativa!B21 -> 5.6921903
A58: 2 | B58: =$B$18+$C$18*A58 -> 18.896926 | C58: 4 | D58: =$B$19+$C$19*C58 -> 9.018787 | G58: Media observada | H58: =B41 -> 13.766667 | I58: =C41 -> 4.3333333
A59: 3 | B59: =$B$18+$C$18*A59 -> 18.425831 | C59: 6 | D59: =$B$19+$C$19*C59 -> 8.7329842
A60: 4 | B60: =$B$18+$C$18*A60 -> 17.954736 | C60: 8 | D60: =$B$19+$C$19*C60 -> 8.4471813
A61: 5 | B61: =$B$18+$C$18*A61 -> 17.483642 | C61: 10 | D61: =$B$19+$C$19*C61 -> 8.1613785
A62: 6 | B62: =$B$18+$C$18*A62 -> 17.012547 | C62: 12 | D62: =$B$19+$C$19*C62 -> 7.8755756
A63: 7 | B63: =$B$18+$C$18*A63 -> 16.541452 | C63: 14 | D63: =$B$19+$C$19*C63 -> 7.5897728
A64: 8 | B64: =$B$18+$C$18*A64 -> 16.070358 | C64: 16 | D64: =$B$19+$C$19*C64 -> 7.3039699
A65: 9 | B65: =$B$18+$C$18*A65 -> 15.599263 | C65: 18 | D65: =$B$19+$C$19*C65 -> 7.0181671
A66: 10 | B66: =$B$18+$C$18*A66 -> 15.128169 | C66: 20 | D66: =$B$19+$C$19*C66 -> 6.7323643
A67: 11 | B67: =$B$18+$C$18*A67 -> 14.657074 | C67: 22 | D67: =$B$19+$C$19*C67 -> 6.4465614
A68: 12 | B68: =$B$18+$C$18*A68 -> 14.185979 | C68: 24 | D68: =$B$19+$C$19*C68 -> 6.1607586
C69: 26 | D69: =$B$19+$C$19*C69 -> 5.8749557
C70: 28 | D70: =$B$19+$C$19*C70 -> 5.5891529
C71: 30 | D71: =$B$19+$C$19*C71 -> 5.3033501

Sheet Cooperativa
A1: Solución cooperativa (maximizar la utilidad conjunta)
A2: Las dos empresas eligen (q1, q2) para maximizar U = u1 + u2, internalizando el daño que cada una causa a la otra.
A4: 1. Parámetros
A5: a1 = α1 − c1 | B5: =Nash!B10 -> 2.8477389
A6: a2 = α2 − c2 | B6: =Nash!D10 -> 4.9506438
A7: β1 | B7: =Nash!B7 -> -0.071770815
A8: β2 | B8: =Nash!D7 -> -0.25810433
A9: Γ = γ1 + γ2 | B9: =Nash!B8+Nash!D8 -> -0.14138864
A11: 2. Problema y condiciones de primer orden
A12: U = u1 + u2 = a1·q1 + a2·q2 + β1·q1² + β2·q2² + (γ1+γ2)·q1·q2
A13: ∂U/∂q1 = a1 + 2β1·q1 + Γ·q2 = 0 ; ∂U/∂q2 = a2 + 2β2·q2 + Γ·q1 = 0
A14: Sistema lineal | B14: q1 | C14: q2 | D14: término indep. (b)
A15: Ecuación 1 | B15: =2*B7 -> -0.14354163 | C15: =B9 -> -0.14138864 | D15: =-B5 -> -2.8477389
A16: Ecuación 2 | B16: =B9 -> -0.14138864 | C16: =2*B8 -> -0.51620867 | D16: =-B6 -> -4.9506438
A17: Determinante = 4β1β2 − Γ² | B17: =B15*C16-C15*B16 -> 0.054106685
A19: 3. Solución cooperativa (por día) – regla de Cramer
A20: q1c Ana (unid/día) | B20: =(D15*C16-C15*D16)/B17 -> 14.232302
A21: q2c Berry (unid/día) | B21: =(B15*D16-D15*B16)/B17 -> 5.6921903
A22: p1c Ana (S/) | B22: =Nash!B6+Nash!B7*B20+Nash!B8*B21 -> 6.9413594
A23: p2c Berry (S/) | B23: =Nash!D6+Nash!D7*B21+Nash!D8*B20 -> 8.7315913
A24: u1c Ana (S/ por día) | B24: =(B22-Nash!B9)*B20 -> 20.513863
A25: u2c Berry (S/ por día) | B25: =(B23-Nash!D9)*B21 -> 13.84108
A26: Uc = u1c + u2c (S/ por día) | B26: =B24+B25 -> 34.354943
A27: Residuo FOC 1 / FOC 2 | B27: =B15*B20+C15*B21-D15 -> 0 | C27: =B16*B20+C16*B21-D16 -> 0
A29: 4. Segundo orden
A30: 2β1 < 0 y 2β2 < 0 y determinante > 0 | B30: =IF(AND(B15<0,C16<0,B17>0),"CUMPLE","REVISAR") -> CUMPLE
A32: 5. Cooperación vs. Nash (por día)
A33: Indicador | B33: Ana | C33: Berry | D33: Conjunto
A34: Utilidad Nash | B34: =Nash!B27 -> 19.36709 | C34: =Nash!B28 -> 13.540241 | D34: =B34+C34 -> 32.907331
A35: Utilidad cooperativa | B35: =B24 -> 20.513863 | C35: =B25 -> 13.84108 | D35: =B35+C35 -> 34.354943
A36: Ganancia (S/ por día) | B36: =B35-B34 -> 1.146773 | C36: =C35-C34 -> 0.30083918 | D36: =D35-D34 -> 1.4476121
A37: Ganancia (%) | B37: =B36/B34 -> 0.059212456 | C37: =C36/C34 -> 0.022218155 | D37: =D36/D34 -> 0.043990566
A38: Ganancia mensual (S/) | B38: =B36*Datos_3J!$B$4 -> 34.403189 | C38: =C36*Datos_3J!$B$4 -> 9.0251753 | D38: =D36*Datos_3J!$B$4 -> 43.428364
A39: ¿Mejora de Pareto? | B39: =IF(AND(B36>0,C36>0),"SÍ: ambas ganan, no hace falta pago lateral",IF(D36>0,"Sólo con pago lateral","NO")) -> SÍ: ambas ganan, no hace falta pago lateral
A41: 6. ¿Es sostenible? Incentivo a desviarse del acuerdo
A42: Si… | B42: Se desvía a q (mejor resp.) | C42: Utilidad del que se desvía | D42: Utilidad del rival | E42: Ganancia por desviarse
A43: Ana se desvía (Berry cumple q2c) | B43: =Nash!B18+Nash!C18*B21 -> 17.157555 | C43: =(Nash!B6+Nash!B7*B43+Nash!B8*B21-Nash!B9)*B43 -> 21.128013 | D43: =(Nash!D6+Nash!D7*B21+Nash!D8*B43-Nash!D9)*B21 -> 12.61278 | E43: =C43-B24 -> 0.61415025
A44: Berry se desvía (Ana cumple q1c) | B44: =Nash!B19+Nash!C19*B20 -> 7.5565765 | C44: =(Nash!D6+Nash!D7*B44+Nash!D8*B20-Nash!D9)*B44 -> 14.738235 | D44: =(Nash!B6+Nash!B7*B20+Nash!B8*B44-Nash!B9)*B20 -> 18.719555 | E44: =C44-B25 -> 0.8971541
A45: Si la ganancia por desviarse es positiva, el acuerdo no se sostiene solo (dilema del prisionero): hace falta repetir el juego, vigilar o castigar. Es la lógica de los juegos repetidos vista en clase.

Sheet Comparativo
A1: Análisis comparativo: observado vs. Nash vs. cooperativo
A2: Valores por día (salvo que se indique). Observado = promedio de los 30 días de la muestra.
A4: Indicador | B4: Observado (media 30 días) | C4: Nash (no cooperativo) | D4: Cooperativo | E4: Coop − Nash | F4: Coop vs. Nash (%)
A5: q1 Ana (unid/día) | B5: =Datos_Comp!$D$42 -> 13.766667 | C5: =Nash!$B$23 -> 16.427 | D5: =Cooperativa!$B$20 -> 14.232302 | E5: =D5-C5 -> -2.1946976 | F5: =IF(C5=0,0,E5/C5) -> -0.13360307
A6: q2 Berry (unid/día) | B6: =Datos_Comp!$E$42 -> 4.3333333 | C6: =Nash!$B$24 -> 7.2429511 | D6: =Cooperativa!$B$21 -> 5.6921903 | E6: =D6-C6 -> -1.5507608 | F6: =IF(C6=0,0,E6/C6) -> -0.21410621
A7: Q total (unid/día) | B7: =B5+B6 -> 18.1 | C7: =C5+C6 -> 23.669951 | D7: =D5+D6 -> 19.924492 | E7: =D7-C7 -> -3.7454584 | F7: =IF(C7=0,0,E7/C7) -> -0.15823685
A8: p1 Ana (S/) | B8: =Datos_Comp!$F$42 -> 7.0666667 | C8: =Nash!$B$25 -> 6.6789791 | D8: =Cooperativa!$B$22 -> 6.9413594 | E8: =D8-C8 -> 0.2623803 | F8: =IF(C8=0,0,E8/C8) -> 0.039284491
A9: p2 Berry (S/) | B9: =Datos_Comp!$G$42 -> 9.1166667 | C9: =Nash!$B$26 -> 8.1694371 | D9: =Cooperativa!$B$23 -> 8.7315913 | E9: =D9-C9 -> 0.56215423 | F9: =IF(C9=0,0,E9/C9) -> 0.068811868
A10: u1 Ana (S/ por día) | B10: =Datos_Comp!$H$42 -> 18.283333 | C10: =Nash!$B$27 -> 19.36709 | D10: =Cooperativa!$B$24 -> 20.513863 | E10: =D10-C10 -> 1.146773 | F10: =IF(C10=0,0,E10/C10) -> 0.059212456
A11: u2 Berry (S/ por día) | B11: =Datos_Comp!$I$42 -> 10.866667 | C11: =Nash!$B$28 -> 13.540241 | D11: =Cooperativa!$B$25 -> 13.84108 | E11: =D11-C11 -> 0.30083918 | F11: =IF(C11=0,0,E11/C11) -> 0.022218155
A12: U conjunta (S/ por día) | B12: =B10+B11 -> 29.15 | C12: =C10+C11 -> 32.907331 | D12: =D10+D11 -> 34.354943 | E12: =D12-C12 -> 1.4476121 | F12: =IF(C12=0,0,E12/C12) -> 0.043990566
A13: u1 Ana (S/ por mes) | B13: =B10*Datos_3J!$B$4 -> 548.5 | C13: =C10*Datos_3J!$B$4 -> 581.01269 | D13: =D10*Datos_3J!$B$4 -> 615.41588 | E13: =D13-C13 -> 34.403189 | F13: =IF(C13=0,0,E13/C13) -> 0.059212456
A14: u2 Berry (S/ por mes) | B14: =B11*Datos_3J!$B$4 -> 326 | C14: =C11*Datos_3J!$B$4 -> 406.20724 | D14: =D11*Datos_3J!$B$4 -> 415.23241 | E14: =D14-C14 -> 9.0251753 | F14: =IF(C14=0,0,E14/C14) -> 0.022218155
A15: U conjunta (S/ por mes) | B15: =B12*Datos_3J!$B$4 -> 874.5 | C15: =C12*Datos_3J!$B$4 -> 987.21993 | D15: =D12*Datos_3J!$B$4 -> 1030.6483 | E15: =D15-C15 -> 43.428364 | F15: =IF(C15=0,0,E15/C15) -> 0.043990566
A17: Lectura (texto con cifras vinculadas)
A18: ="1) Cantidades: en Nash Ana vende "&TEXT(C5,"0.0")&" y Berry "&TEXT(C6,"0.0")&" unid/día; cooperando bajan a "&TEXT(D5,"0.0")&" y "&TEXT(D6,"0.0")&" ("&TEXT(F7,"0.0%")&" en total): cooperar es producir menos para vender más caro." -> 1) Cantidades: en Nash Ana vende 16.4 y Berry 7.2 unid/día; cooperando bajan a 14.2 y 5.7 (-15.8% en total): cooperar es producir menos para vender más caro.
A19: ="2) Precios: p1 pasa de "&TEXT(C8,"0.00")&" a "&TEXT(D8,"0.00")&" y p2 de "&TEXT(C9,"0.00")&" a "&TEXT(D9,"0.00")&" soles." -> 2) Precios: p1 pasa de 6.68 a 6.94 y p2 de 8.17 a 8.73 soles.
A20: ="3) Utilidades: Ana "&TEXT(C10,"0.00")&" → "&TEXT(D10,"0.00")&" ("&TEXT(F10,"+0.0%;-0.0%")&"), Berry "&TEXT(C11,"0.00")&" → "&TEXT(D11,"0.00")&" ("&TEXT(F11,"+0.0%;-0.0%")&"); conjunta "&TEXT(C12,"0.00")&" → "&TEXT(D12,"0.00")&" soles/día ("&TEXT(E15,"#,##0")&" soles al mes)." -> 3) Utilidades: Ana 19.37 → 20.51 (+5.9%), Berry 13.54 → 13.84 (+2.2%); conjunta 32.91 → 34.35 soles/día (43 soles al mes).
A21: ="4) Frente a lo observado (promedio de 30 días): Ana vende "&TEXT(B5,"0.0")&" a S/ "&TEXT(B8,"0.00")&" y Berry "&TEXT(B6,"0.0")&" a S/ "&TEXT(B9,"0.00")&"; sus utilidades diarias observadas ("&TEXT(B10,"0.00")&" y "&TEXT(B11,"0.00")&") quedan "&IF(AND(B10<C10,B11<C11),"por debajo","en torno o por encima")&" de las de Nash ("&TEXT(C10,"0.00")&" y "&TEXT(C11,"0.00")&")." -> 4) Frente a lo observado (promedio de 30 días): Ana vende 13.8 a S/ 7.07 y Berry 4.3 a S/ 9.12; sus utilidades diarias observadas (18.28 y 10.87) quedan por debajo de las de Nash (19.37 y 13.54).
